{
  "displayColumn": "name",
  "isReactive": true,
  "meta": {
    "cost": {
      "Width": "119px",
      "displayName": "Cost",
      "invisible": false,
      "order": 3,
      "priceFormat": true,
      "type": "number"
    },
    "createdDate": {
      "displayName": "Created Date",
      "invisible": true,
      "order": 8,
      "type": "date"
    },
    "lastEditDate": {
      "displayName": "Last edit date",
      "invisible": true,
      "order": 12,
      "type": "date"
    },
    "lastEditedBy": {
      "displayName": "Last edited by",
      "invisible": true,
      "order": 11,
      "type": "user"
    },
    "layout": {
      "displayName": "Layout",
      "invisible": true,
      "order": 6,
      "type": "select"
    },
    "name": {
      "displayName": "Name",
      "invisible": false,
      "order": 0,
      "type": "string"
    },
    "nextEvents": {
      "displayName": "Next Events",
      "invisible": true,
      "order": 10,
      "type": "string"
    },
    "owner": {
      "displayName": "Owner",
      "invisible": true,
      "order": 7,
      "type": "user"
    },
    "part": {
      "Width": "186px",
      "displayName": "Part",
      "invisible": false,
      "lookUpTable": "parts",
      "order": 1,
      "type": "lookup"
    },
    "quantity": {
      "Width": "148px",
      "displayName": "Quantity Per",
      "invisible": false,
      "order": 2,
      "type": "number"
    },
    "quoteLine": {
      "Width": "182px",
      "displayName": "Quote Line",
      "indexed": true,
      "invisible": false,
      "lookUpTable": "quoteLines",
      "order": 13,
      "type": "lookup"
    },
    "quoteNumber": {
      "displayName": "Quote Number",
      "invisible": true,
      "order": 15,
      "type": "string"
    },
    "salesLine": {
      "displayName": "Sales Line",
      "indexed": true,
      "invisible": true,
      "lookUpTable": "salesLines",
      "order": 14,
      "type": "lookup"
    },
    "state": {
      "displayName": "State",
      "invisible": true,
      "order": 9,
      "type": "string"
    },
    "total": {
      "Width": "114px",
      "displayName": "Total",
      "invisible": false,
      "order": 4,
      "priceFormat": true,
      "type": "number"
    },
    "uoM": {
      "Width": "234px",
      "displayName": "UoM",
      "invisible": false,
      "lookUpTable": "unitsOfMeasure",
      "order": 5,
      "type": "lookup"
    },
    "vendor": {
      "displayName": "Vendor",
      "indexed": true,
      "invisible": true,
      "lookUpTable": "vendors",
      "order": 16,
      "type": "lookup"
    }
  },
  "rowEditorFieldsForm": {
    "sections": [
      {
        "name": "section_824067",
        "label": "Estimate Material",
        "clientKey": "section_824067",
        "order": 0,
        "rows": [
          {
            "name": "section_824067_row_659565",
            "label": "",
            "order": 0,
            "controls": [
              {
                "type": "text",
                "name": "control_1dd803b2-c104-11ee-8433-4f93c020f70e",
                "fieldName": "control_1dd803b2-c104-11ee-8433-4f93c020f70e",
                "label": "Name",
                "order": 0,
                "defaultValue": "",
                "value": "",
                "className": "col-md-6",
                "readonly": false,
                "readonlyCondition": "",
                "placeholder": "",
                "required": false,
                "requiredCondition": "",
                "isMultiLine": false,
                "isInteger": false,
                "decimalPlace": 2,
                "isTodayValue": false,
                "isTodayValueCreated": true,
                "dateFormat": "mm/dd/yy hh:mm p",
                "timezone": null,
                "selectedDataGrid": null,
                "printedFileName": null,
                "buttonLabel": "",
                "dataForTemplate": null,
                "selectedOutputDataGrid": null,
                "templateRowKey": null,
                "isForDownload": false,
                "openInNewTab": false,
                "attachRecord": false,
                "isCurrentUser": false,
                "isCurrentUserOwner": true,
                "isNowTimeValue": false,
                "timeFormat": "HH:mm",
                "isMultiple": false,
                "isAjax": false,
                "dataOptions": [],
                "ajaxDataUrl": "",
                "isChecked": false,
                "vif": "",
                "customCode": "",
                "invisible": false,
                "invisibleCondition": "",
                "invisibleLabel": false,
                "enableCustomValidation": false,
                "customValidationRule": "",
                "customValidationErrorMessage": "",
                "mask": "",
                "lookupOpenInModalDisabled": false,
                "editorMode": "javascript",
                "dataGridAvailableViews": [],
                "dataGridView": null,
                "dataGridAddRecordsText": "",
                "dataGridAddRecordText": "",
                "skipCrop": false,
                "disableRoundedStyle": false,
                "propName": "name",
                "gridId": "estimateMaterials",
                "sum": true,
                "expression": "rowData.part && rowData.$part.name"
              },
              {
                "type": "text",
                "name": "control_a0364190-96fc-11ef-b774-ddb2a337b1a9",
                "fieldName": "control_a0364190-96fc-11ef-b774-ddb2a337b1a9",
                "label": "Quote Number",
                "order": 0,
                "defaultValue": "",
                "value": "",
                "className": "col-md-6",
                "readonly": false,
                "readonlyCondition": "",
                "placeholder": "",
                "required": false,
                "requiredCondition": "",
                "isMultiLine": false,
                "isInteger": false,
                "decimalPlace": 2,
                "expression": "",
                "oneDriveFileId": null,
                "isTodayValue": false,
                "isTodayValueCreated": true,
                "dateFormat": "mm/dd/yy hh:mm p",
                "timezone": null,
                "selectedDataGrid": null,
                "printedFileName": null,
                "buttonLabel": "",
                "dataForTemplate": null,
                "selectedOutputDataGrid": null,
                "templateRowKey": null,
                "isForDownload": false,
                "isOneDriveTemplate": false,
                "selectedOneDriveFile": null,
                "openInNewTab": false,
                "attachRecord": false,
                "isCurrentUser": false,
                "isCurrentUserOwner": true,
                "isNowTimeValue": false,
                "timeFormat": "HH:mm",
                "isMultiple": false,
                "isAjax": false,
                "dataOptions": [],
                "ajaxDataUrl": "",
                "isChecked": false,
                "vif": "",
                "customCode": "",
                "invisible": false,
                "invisibleCondition": "",
                "invisibleLabel": false,
                "enableCustomValidation": false,
                "customValidationRule": "",
                "customValidationErrorMessage": "",
                "mask": "",
                "lookupOpenInModalDisabled": false,
                "lookUpSearch": null,
                "editorMode": "javascript",
                "dataGridAvailableViews": [],
                "dataGridView": null,
                "dataGridAddRecordsText": "",
                "dataGridAddRecordText": "",
                "skipCrop": false,
                "disableRoundedStyle": false,
                "propName": "quoteNumber"
              },
              {
                "type": "lookup",
                "name": "control_9eb758f0-c104-11ee-8433-4f93c020f70e",
                "fieldName": "control_9eb758f0-c104-11ee-8433-4f93c020f70e",
                "label": "Quote Line",
                "order": 0,
                "defaultValue": "",
                "value": "",
                "className": "col-md-6",
                "readonly": false,
                "readonlyCondition": "",
                "placeholder": "",
                "required": false,
                "requiredCondition": "",
                "isMultiLine": false,
                "isInteger": false,
                "decimalPlace": 2,
                "isTodayValue": false,
                "isTodayValueCreated": true,
                "dateFormat": "mm/dd/yy hh:mm p",
                "timezone": null,
                "selectedDataGrid": null,
                "printedFileName": null,
                "buttonLabel": "",
                "dataForTemplate": null,
                "selectedOutputDataGrid": null,
                "templateRowKey": null,
                "isForDownload": false,
                "openInNewTab": false,
                "attachRecord": false,
                "isCurrentUser": false,
                "isCurrentUserOwner": true,
                "isNowTimeValue": false,
                "timeFormat": "HH:mm",
                "isMultiple": false,
                "isAjax": false,
                "dataOptions": [],
                "ajaxDataUrl": "",
                "isChecked": false,
                "vif": "",
                "customCode": "",
                "invisible": false,
                "invisibleCondition": "",
                "invisibleLabel": false,
                "enableCustomValidation": false,
                "customValidationRule": "",
                "customValidationErrorMessage": "",
                "mask": "",
                "lookupOpenInModalDisabled": false,
                "editorMode": "javascript",
                "dataGridAvailableViews": [],
                "dataGridView": null,
                "dataGridAddRecordsText": "",
                "dataGridAddRecordText": "",
                "skipCrop": false,
                "disableRoundedStyle": false,
                "propName": "quoteLine",
                "ableToAddLookUpVal": true
              },
              {
                "type": "lookup",
                "name": "control_a6ddbf50-96fc-11ef-b774-ddb2a337b1a9",
                "fieldName": "control_a6ddbf50-96fc-11ef-b774-ddb2a337b1a9",
                "label": "Vendor",
                "order": 0,
                "defaultValue": "",
                "value": "",
                "className": "col-md-6",
                "readonly": false,
                "readonlyCondition": "",
                "placeholder": "",
                "required": false,
                "requiredCondition": "",
                "isMultiLine": false,
                "isInteger": false,
                "decimalPlace": 2,
                "expression": "",
                "oneDriveFileId": null,
                "isTodayValue": false,
                "isTodayValueCreated": true,
                "dateFormat": "mm/dd/yy hh:mm p",
                "timezone": null,
                "selectedDataGrid": null,
                "printedFileName": null,
                "buttonLabel": "",
                "dataForTemplate": null,
                "selectedOutputDataGrid": null,
                "templateRowKey": null,
                "isForDownload": false,
                "isOneDriveTemplate": false,
                "selectedOneDriveFile": null,
                "openInNewTab": false,
                "attachRecord": false,
                "isCurrentUser": false,
                "isCurrentUserOwner": true,
                "isNowTimeValue": false,
                "timeFormat": "HH:mm",
                "isMultiple": false,
                "isAjax": false,
                "dataOptions": [],
                "ajaxDataUrl": "",
                "isChecked": false,
                "vif": "",
                "customCode": "",
                "invisible": false,
                "invisibleCondition": "",
                "invisibleLabel": false,
                "enableCustomValidation": false,
                "customValidationRule": "",
                "customValidationErrorMessage": "",
                "mask": "",
                "lookupOpenInModalDisabled": false,
                "lookUpSearch": null,
                "editorMode": "javascript",
                "dataGridAvailableViews": [],
                "dataGridView": null,
                "dataGridAddRecordsText": "",
                "dataGridAddRecordText": "",
                "skipCrop": false,
                "disableRoundedStyle": false,
                "propName": "vendor",
                "ableToAddLookUpVal": true
              },
              {
                "type": "lookup",
                "name": "control_c8b689a0-c104-11ee-8433-4f93c020f70e",
                "fieldName": "control_c8b689a0-c104-11ee-8433-4f93c020f70e",
                "label": "Part",
                "order": 0,
                "defaultValue": "",
                "value": "",
                "className": "col-md-6",
                "readonly": false,
                "readonlyCondition": "",
                "placeholder": "",
                "required": false,
                "requiredCondition": "",
                "isMultiLine": false,
                "isInteger": false,
                "decimalPlace": 2,
                "isTodayValue": false,
                "isTodayValueCreated": true,
                "dateFormat": "mm/dd/yy hh:mm p",
                "timezone": null,
                "selectedDataGrid": null,
                "printedFileName": null,
                "buttonLabel": "",
                "dataForTemplate": null,
                "selectedOutputDataGrid": null,
                "templateRowKey": null,
                "isForDownload": false,
                "openInNewTab": false,
                "attachRecord": false,
                "isCurrentUser": false,
                "isCurrentUserOwner": true,
                "isNowTimeValue": false,
                "timeFormat": "HH:mm",
                "isMultiple": false,
                "isAjax": false,
                "dataOptions": [],
                "ajaxDataUrl": "",
                "isChecked": false,
                "vif": "",
                "customCode": "",
                "invisible": false,
                "invisibleCondition": "",
                "invisibleLabel": false,
                "enableCustomValidation": false,
                "customValidationRule": "",
                "customValidationErrorMessage": "",
                "mask": "",
                "lookupOpenInModalDisabled": false,
                "editorMode": "javascript",
                "dataGridAvailableViews": [],
                "dataGridView": null,
                "dataGridAddRecordsText": "",
                "dataGridAddRecordText": "",
                "skipCrop": false,
                "disableRoundedStyle": false,
                "propName": "part",
                "ableToAddLookUpVal": true,
                "gridId": "estimateMaterials",
                "lookUpSearch": "partDemand"
              },
              {
                "type": "number",
                "name": "control_cedfafa0-c104-11ee-8433-4f93c020f70e",
                "fieldName": "control_cedfafa0-c104-11ee-8433-4f93c020f70e",
                "label": "Quantity Per",
                "order": 0,
                "defaultValue": "1",
                "value": "",
                "className": "col-md-6",
                "readonly": false,
                "readonlyCondition": "",
                "placeholder": "",
                "required": false,
                "requiredCondition": "",
                "isMultiLine": false,
                "isInteger": false,
                "decimalPlace": 2,
                "isTodayValue": false,
                "isTodayValueCreated": true,
                "dateFormat": "mm/dd/yy hh:mm p",
                "timezone": null,
                "selectedDataGrid": null,
                "printedFileName": null,
                "buttonLabel": "",
                "dataForTemplate": null,
                "selectedOutputDataGrid": null,
                "templateRowKey": null,
                "isForDownload": false,
                "openInNewTab": false,
                "attachRecord": false,
                "isCurrentUser": false,
                "isCurrentUserOwner": true,
                "isNowTimeValue": false,
                "timeFormat": "HH:mm",
                "isMultiple": false,
                "isAjax": false,
                "dataOptions": [],
                "ajaxDataUrl": "",
                "isChecked": false,
                "vif": "",
                "customCode": "",
                "invisible": false,
                "invisibleCondition": "",
                "invisibleLabel": false,
                "enableCustomValidation": false,
                "customValidationRule": "",
                "customValidationErrorMessage": "",
                "mask": "",
                "lookupOpenInModalDisabled": false,
                "editorMode": "javascript",
                "dataGridAvailableViews": [],
                "dataGridView": null,
                "dataGridAddRecordsText": "",
                "dataGridAddRecordText": "",
                "skipCrop": false,
                "disableRoundedStyle": false,
                "propName": "quantity",
                "gridId": "estimateMaterials"
              },
              {
                "type": "number",
                "name": "control_d65f3de0-c104-11ee-8433-4f93c020f70e",
                "fieldName": "control_d65f3de0-c104-11ee-8433-4f93c020f70e",
                "label": "Cost",
                "order": 0,
                "defaultValue": "",
                "value": "",
                "className": "col-md-6",
                "readonly": false,
                "readonlyCondition": "",
                "placeholder": "",
                "required": false,
                "requiredCondition": "",
                "isMultiLine": false,
                "isInteger": false,
                "decimalPlace": 2,
                "isTodayValue": false,
                "isTodayValueCreated": true,
                "dateFormat": "mm/dd/yy hh:mm p",
                "timezone": null,
                "selectedDataGrid": null,
                "printedFileName": null,
                "buttonLabel": "",
                "dataForTemplate": null,
                "selectedOutputDataGrid": null,
                "templateRowKey": null,
                "isForDownload": false,
                "openInNewTab": false,
                "attachRecord": false,
                "isCurrentUser": false,
                "isCurrentUserOwner": true,
                "isNowTimeValue": false,
                "timeFormat": "HH:mm",
                "isMultiple": false,
                "isAjax": false,
                "dataOptions": [],
                "ajaxDataUrl": "",
                "isChecked": false,
                "vif": "",
                "customCode": "",
                "invisible": false,
                "invisibleCondition": "",
                "invisibleLabel": false,
                "enableCustomValidation": false,
                "customValidationRule": "",
                "customValidationErrorMessage": "",
                "mask": "",
                "lookupOpenInModalDisabled": false,
                "editorMode": "javascript",
                "dataGridAvailableViews": [],
                "dataGridView": null,
                "dataGridAddRecordsText": "",
                "dataGridAddRecordText": "",
                "skipCrop": false,
                "disableRoundedStyle": false,
                "propName": "cost"
              },
              {
                "type": "number",
                "name": "control_de94d5b0-c104-11ee-8433-4f93c020f70e",
                "fieldName": "control_de94d5b0-c104-11ee-8433-4f93c020f70e",
                "label": "Total",
                "order": 0,
                "defaultValue": "",
                "value": "",
                "className": "col-md-6",
                "readonly": false,
                "readonlyCondition": "",
                "placeholder": "",
                "required": false,
                "requiredCondition": "",
                "isMultiLine": false,
                "isInteger": false,
                "decimalPlace": 2,
                "isTodayValue": false,
                "isTodayValueCreated": true,
                "dateFormat": "mm/dd/yy hh:mm p",
                "timezone": null,
                "selectedDataGrid": null,
                "printedFileName": null,
                "buttonLabel": "",
                "dataForTemplate": null,
                "selectedOutputDataGrid": null,
                "templateRowKey": null,
                "isForDownload": false,
                "openInNewTab": false,
                "attachRecord": false,
                "isCurrentUser": false,
                "isCurrentUserOwner": true,
                "isNowTimeValue": false,
                "timeFormat": "HH:mm",
                "isMultiple": false,
                "isAjax": false,
                "dataOptions": [],
                "ajaxDataUrl": "",
                "isChecked": false,
                "vif": "",
                "customCode": "",
                "invisible": false,
                "invisibleCondition": "",
                "invisibleLabel": false,
                "enableCustomValidation": false,
                "customValidationRule": "",
                "customValidationErrorMessage": "",
                "mask": "",
                "lookupOpenInModalDisabled": false,
                "editorMode": "javascript",
                "dataGridAvailableViews": [],
                "dataGridView": null,
                "dataGridAddRecordsText": "",
                "dataGridAddRecordText": "",
                "skipCrop": false,
                "disableRoundedStyle": false,
                "propName": "total"
              },
              {
                "type": "lookup",
                "name": "control_25f53c10-c105-11ee-8433-4f93c020f70e",
                "fieldName": "control_25f53c10-c105-11ee-8433-4f93c020f70e",
                "label": "UoM",
                "order": 0,
                "defaultValue": "",
                "value": "",
                "className": "col-md-6",
                "readonly": false,
                "readonlyCondition": "",
                "placeholder": "",
                "required": false,
                "requiredCondition": "",
                "isMultiLine": false,
                "isInteger": false,
                "decimalPlace": 2,
                "isTodayValue": false,
                "isTodayValueCreated": true,
                "dateFormat": "mm/dd/yy hh:mm p",
                "timezone": null,
                "selectedDataGrid": null,
                "printedFileName": null,
                "buttonLabel": "",
                "dataForTemplate": null,
                "selectedOutputDataGrid": null,
                "templateRowKey": null,
                "isForDownload": false,
                "openInNewTab": false,
                "attachRecord": false,
                "isCurrentUser": false,
                "isCurrentUserOwner": true,
                "isNowTimeValue": false,
                "timeFormat": "HH:mm",
                "isMultiple": false,
                "isAjax": false,
                "dataOptions": [],
                "ajaxDataUrl": "",
                "isChecked": false,
                "vif": "",
                "customCode": "",
                "invisible": false,
                "invisibleCondition": "",
                "invisibleLabel": false,
                "enableCustomValidation": false,
                "customValidationRule": "",
                "customValidationErrorMessage": "",
                "mask": "",
                "lookupOpenInModalDisabled": false,
                "editorMode": "javascript",
                "dataGridAvailableViews": [],
                "dataGridView": null,
                "dataGridAddRecordsText": "",
                "dataGridAddRecordText": "",
                "skipCrop": false,
                "disableRoundedStyle": false,
                "propName": "uoM",
                "ableToAddLookUpVal": true
              },
              {
                "type": "lookup",
                "name": "control_b927bcf0-c1d8-11ee-99a2-8d4194ff50ca",
                "fieldName": "control_b927bcf0-c1d8-11ee-99a2-8d4194ff50ca",
                "label": "Sales Line",
                "order": 0,
                "defaultValue": "",
                "value": "",
                "className": "col-md-6",
                "readonly": false,
                "readonlyCondition": "",
                "placeholder": "",
                "required": false,
                "requiredCondition": "",
                "isMultiLine": false,
                "isInteger": false,
                "decimalPlace": 2,
                "isTodayValue": false,
                "isTodayValueCreated": true,
                "dateFormat": "mm/dd/yy hh:mm p",
                "timezone": null,
                "selectedDataGrid": null,
                "printedFileName": null,
                "buttonLabel": "",
                "dataForTemplate": null,
                "selectedOutputDataGrid": null,
                "templateRowKey": null,
                "isForDownload": false,
                "openInNewTab": false,
                "attachRecord": false,
                "isCurrentUser": false,
                "isCurrentUserOwner": true,
                "isNowTimeValue": false,
                "timeFormat": "HH:mm",
                "isMultiple": false,
                "isAjax": false,
                "dataOptions": [],
                "ajaxDataUrl": "",
                "isChecked": false,
                "vif": "",
                "customCode": "",
                "invisible": false,
                "invisibleCondition": "",
                "invisibleLabel": false,
                "enableCustomValidation": false,
                "customValidationRule": "",
                "customValidationErrorMessage": "",
                "mask": "",
                "lookupOpenInModalDisabled": false,
                "editorMode": "javascript",
                "dataGridAvailableViews": [],
                "dataGridView": null,
                "dataGridAddRecordsText": "",
                "dataGridAddRecordText": "",
                "skipCrop": false,
                "disableRoundedStyle": false,
                "propName": "salesLine",
                "ableToAddLookUpVal": true
              }
            ]
          }
        ],
        "labelPosition": "top",
        "isDynamic": false,
        "minInstance": 1,
        "maxInstance": 0,
        "instances": []
      },
      {
        "cleintKey": "hidden_section_1dd803b0-c104-11ee-8433-4f93c020f70e",
        "instances": [],
        "isDynamic": false,
        "label": "Hidden Section",
        "vif": "false",
        "name": "hidden_section_1dd803b0-c104-11ee-8433-4f93c020f70e",
        "order": 1,
        "rows": [
          {
            "name": "hidden_section_1dd803b0-c104-11ee-8433-4f93c020f70e_row_1dd803b1-c104-11ee-8433-4f93c020f70e",
            "controls": [
              {
                "type": "select",
                "name": "control_1e1cfbf0-c104-11ee-8433-4f93c020f70e",
                "fieldName": "control_1e1cfbf0-c104-11ee-8433-4f93c020f70e",
                "label": "Layout",
                "order": 0,
                "defaultValue": "",
                "value": "",
                "className": "col-md-6",
                "readonly": false,
                "readonlyCondition": "",
                "placeholder": "",
                "required": false,
                "requiredCondition": "",
                "isMultiLine": false,
                "isInteger": false,
                "decimalPlace": 2,
                "isTodayValue": false,
                "isTodayValueCreated": true,
                "dateFormat": "mm/dd/yy hh:mm p",
                "timezone": null,
                "selectedDataGrid": null,
                "printedFileName": null,
                "buttonLabel": "",
                "dataForTemplate": null,
                "selectedOutputDataGrid": null,
                "templateRowKey": null,
                "isForDownload": false,
                "openInNewTab": false,
                "attachRecord": false,
                "isCurrentUser": false,
                "isCurrentUserOwner": true,
                "isNowTimeValue": false,
                "timeFormat": "HH:mm",
                "isMultiple": false,
                "isAjax": false,
                "dataOptions": [],
                "ajaxDataUrl": "",
                "isChecked": false,
                "vif": "",
                "customCode": "",
                "invisible": true,
                "invisibleCondition": "",
                "invisibleLabel": false,
                "enableCustomValidation": false,
                "customValidationRule": "",
                "customValidationErrorMessage": "",
                "mask": "",
                "lookupOpenInModalDisabled": false,
                "editorMode": "javascript",
                "dataGridAvailableViews": [],
                "dataGridView": null,
                "dataGridAddRecordsText": "",
                "dataGridAddRecordText": "",
                "skipCrop": false,
                "disableRoundedStyle": false,
                "propName": "layout"
              },
              {
                "type": "user",
                "name": "control_1e568280-c104-11ee-8433-4f93c020f70e",
                "fieldName": "control_1e568280-c104-11ee-8433-4f93c020f70e",
                "label": "Owner",
                "order": 0,
                "defaultValue": "",
                "value": "",
                "className": "col-md-6",
                "readonly": false,
                "readonlyCondition": "",
                "placeholder": "",
                "required": false,
                "requiredCondition": "",
                "isMultiLine": false,
                "isInteger": false,
                "decimalPlace": 2,
                "isTodayValue": false,
                "isTodayValueCreated": true,
                "dateFormat": "mm/dd/yy hh:mm p",
                "timezone": null,
                "selectedDataGrid": null,
                "printedFileName": null,
                "buttonLabel": "",
                "dataForTemplate": null,
                "selectedOutputDataGrid": null,
                "templateRowKey": null,
                "isForDownload": false,
                "openInNewTab": false,
                "attachRecord": false,
                "isCurrentUser": false,
                "isCurrentUserOwner": true,
                "isNowTimeValue": false,
                "timeFormat": "HH:mm",
                "isMultiple": false,
                "isAjax": false,
                "dataOptions": [],
                "ajaxDataUrl": "",
                "isChecked": false,
                "vif": "",
                "customCode": "",
                "invisible": true,
                "invisibleCondition": "",
                "invisibleLabel": false,
                "enableCustomValidation": false,
                "customValidationRule": "",
                "customValidationErrorMessage": "",
                "mask": "",
                "lookupOpenInModalDisabled": false,
                "editorMode": "javascript",
                "dataGridAvailableViews": [],
                "dataGridView": null,
                "dataGridAddRecordsText": "",
                "dataGridAddRecordText": "",
                "skipCrop": false,
                "disableRoundedStyle": false,
                "propName": "owner"
              },
              {
                "type": "datepicker",
                "name": "control_1ef55a90-c104-11ee-8433-4f93c020f70e",
                "fieldName": "control_1ef55a90-c104-11ee-8433-4f93c020f70e",
                "label": "Created Date",
                "order": 0,
                "defaultValue": "",
                "value": "",
                "className": "col-md-6",
                "readonly": false,
                "readonlyCondition": "",
                "placeholder": "",
                "required": false,
                "requiredCondition": "",
                "isMultiLine": false,
                "isInteger": false,
                "decimalPlace": 2,
                "isTodayValue": false,
                "isTodayValueCreated": true,
                "dateFormat": "mm/dd/yy hh:mm p",
                "timezone": null,
                "selectedDataGrid": null,
                "printedFileName": null,
                "buttonLabel": "",
                "dataForTemplate": null,
                "selectedOutputDataGrid": null,
                "templateRowKey": null,
                "isForDownload": false,
                "openInNewTab": false,
                "attachRecord": false,
                "isCurrentUser": false,
                "isCurrentUserOwner": true,
                "isNowTimeValue": false,
                "timeFormat": "HH:mm",
                "isMultiple": false,
                "isAjax": false,
                "dataOptions": [],
                "ajaxDataUrl": "",
                "isChecked": false,
                "vif": "",
                "customCode": "",
                "invisible": true,
                "invisibleCondition": "",
                "invisibleLabel": false,
                "enableCustomValidation": false,
                "customValidationRule": "",
                "customValidationErrorMessage": "",
                "mask": "",
                "lookupOpenInModalDisabled": false,
                "editorMode": "javascript",
                "dataGridAvailableViews": [],
                "dataGridView": null,
                "dataGridAddRecordsText": "",
                "dataGridAddRecordText": "",
                "skipCrop": false,
                "disableRoundedStyle": false,
                "propName": "createdDate"
              },
              {
                "type": "text",
                "name": "control_1f4157b0-c104-11ee-8433-4f93c020f70e",
                "fieldName": "control_1f4157b0-c104-11ee-8433-4f93c020f70e",
                "label": "State",
                "order": 0,
                "defaultValue": "",
                "value": "",
                "className": "col-md-6",
                "readonly": false,
                "readonlyCondition": "",
                "placeholder": "",
                "required": false,
                "requiredCondition": "",
                "isMultiLine": false,
                "isInteger": false,
                "decimalPlace": 2,
                "isTodayValue": false,
                "isTodayValueCreated": true,
                "dateFormat": "mm/dd/yy hh:mm p",
                "timezone": null,
                "selectedDataGrid": null,
                "printedFileName": null,
                "buttonLabel": "",
                "dataForTemplate": null,
                "selectedOutputDataGrid": null,
                "templateRowKey": null,
                "isForDownload": false,
                "openInNewTab": false,
                "attachRecord": false,
                "isCurrentUser": false,
                "isCurrentUserOwner": true,
                "isNowTimeValue": false,
                "timeFormat": "HH:mm",
                "isMultiple": false,
                "isAjax": false,
                "dataOptions": [],
                "ajaxDataUrl": "",
                "isChecked": false,
                "vif": "",
                "customCode": "",
                "invisible": true,
                "invisibleCondition": "",
                "invisibleLabel": false,
                "enableCustomValidation": false,
                "customValidationRule": "",
                "customValidationErrorMessage": "",
                "mask": "",
                "lookupOpenInModalDisabled": false,
                "editorMode": "javascript",
                "dataGridAvailableViews": [],
                "dataGridView": null,
                "dataGridAddRecordsText": "",
                "dataGridAddRecordText": "",
                "skipCrop": false,
                "disableRoundedStyle": false,
                "propName": "state"
              },
              {
                "type": "text",
                "name": "control_1f820a30-c104-11ee-8433-4f93c020f70e",
                "fieldName": "control_1f820a30-c104-11ee-8433-4f93c020f70e",
                "label": "Next Events",
                "order": 0,
                "defaultValue": "",
                "value": "",
                "className": "col-md-6",
                "readonly": false,
                "readonlyCondition": "",
                "placeholder": "",
                "required": false,
                "requiredCondition": "",
                "isMultiLine": false,
                "isInteger": false,
                "decimalPlace": 2,
                "isTodayValue": false,
                "isTodayValueCreated": true,
                "dateFormat": "mm/dd/yy hh:mm p",
                "timezone": null,
                "selectedDataGrid": null,
                "printedFileName": null,
                "buttonLabel": "",
                "dataForTemplate": null,
                "selectedOutputDataGrid": null,
                "templateRowKey": null,
                "isForDownload": false,
                "openInNewTab": false,
                "attachRecord": false,
                "isCurrentUser": false,
                "isCurrentUserOwner": true,
                "isNowTimeValue": false,
                "timeFormat": "HH:mm",
                "isMultiple": false,
                "isAjax": false,
                "dataOptions": [],
                "ajaxDataUrl": "",
                "isChecked": false,
                "vif": "",
                "customCode": "",
                "invisible": true,
                "invisibleCondition": "",
                "invisibleLabel": false,
                "enableCustomValidation": false,
                "customValidationRule": "",
                "customValidationErrorMessage": "",
                "mask": "",
                "lookupOpenInModalDisabled": false,
                "editorMode": "javascript",
                "dataGridAvailableViews": [],
                "dataGridView": null,
                "dataGridAddRecordsText": "",
                "dataGridAddRecordText": "",
                "skipCrop": false,
                "disableRoundedStyle": false,
                "propName": "nextEvents"
              },
              {
                "type": "user",
                "name": "control_1fc2bcb0-c104-11ee-8433-4f93c020f70e",
                "fieldName": "control_1fc2bcb0-c104-11ee-8433-4f93c020f70e",
                "label": "Last edited by",
                "order": 0,
                "defaultValue": "",
                "value": "",
                "className": "col-md-6",
                "readonly": true,
                "readonlyCondition": "",
                "placeholder": "",
                "required": false,
                "requiredCondition": "",
                "isMultiLine": false,
                "isInteger": false,
                "decimalPlace": 2,
                "isTodayValue": false,
                "isTodayValueCreated": true,
                "dateFormat": "mm/dd/yy hh:mm p",
                "timezone": null,
                "selectedDataGrid": null,
                "printedFileName": null,
                "buttonLabel": "",
                "dataForTemplate": null,
                "selectedOutputDataGrid": null,
                "templateRowKey": null,
                "isForDownload": false,
                "openInNewTab": false,
                "attachRecord": false,
                "isCurrentUser": false,
                "isCurrentUserOwner": true,
                "isNowTimeValue": false,
                "timeFormat": "HH:mm",
                "isMultiple": false,
                "isAjax": false,
                "dataOptions": [],
                "ajaxDataUrl": "",
                "isChecked": false,
                "vif": "",
                "customCode": "",
                "invisible": true,
                "invisibleCondition": "",
                "invisibleLabel": false,
                "enableCustomValidation": false,
                "customValidationRule": "",
                "customValidationErrorMessage": "",
                "mask": "",
                "lookupOpenInModalDisabled": false,
                "editorMode": "javascript",
                "dataGridAvailableViews": [],
                "dataGridView": null,
                "dataGridAddRecordsText": "",
                "dataGridAddRecordText": "",
                "skipCrop": false,
                "disableRoundedStyle": false,
                "propName": "lastEditedBy"
              },
              {
                "type": "datepicker",
                "name": "control_20045990-c104-11ee-8433-4f93c020f70e",
                "fieldName": "control_20045990-c104-11ee-8433-4f93c020f70e",
                "label": "Last edit date",
                "order": 0,
                "defaultValue": "",
                "value": "",
                "className": "col-md-6",
                "readonly": true,
                "readonlyCondition": "",
                "placeholder": "",
                "required": false,
                "requiredCondition": "",
                "isMultiLine": false,
                "isInteger": false,
                "decimalPlace": 2,
                "isTodayValue": false,
                "isTodayValueCreated": true,
                "dateFormat": "mm/dd/yy hh:mm p",
                "timezone": null,
                "selectedDataGrid": null,
                "printedFileName": null,
                "buttonLabel": "",
                "dataForTemplate": null,
                "selectedOutputDataGrid": null,
                "templateRowKey": null,
                "isForDownload": false,
                "openInNewTab": false,
                "attachRecord": false,
                "isCurrentUser": false,
                "isCurrentUserOwner": true,
                "isNowTimeValue": false,
                "timeFormat": "HH:mm",
                "isMultiple": false,
                "isAjax": false,
                "dataOptions": [],
                "ajaxDataUrl": "",
                "isChecked": false,
                "vif": "",
                "customCode": "",
                "invisible": true,
                "invisibleCondition": "",
                "invisibleLabel": false,
                "enableCustomValidation": false,
                "customValidationRule": "",
                "customValidationErrorMessage": "",
                "mask": "",
                "lookupOpenInModalDisabled": false,
                "editorMode": "javascript",
                "dataGridAvailableViews": [],
                "dataGridView": null,
                "dataGridAddRecordsText": "",
                "dataGridAddRecordText": "",
                "skipCrop": false,
                "disableRoundedStyle": false,
                "propName": "lastEditDate"
              }
            ]
          }
        ]
      }
    ],
    "layout": "collapse"
  },
  "source": "estimateMaterials",
  "storageType": "dashboard",
  "title": "Estimate Materials",
  "views": {
    "importexcelview": {
      "displayAsExcel": true,
      "displayCompact": false,
      "displayInTab": false,
      "meta": {
        "cost": {
          "displayName": "Cost",
          "invisible": false,
          "order": 3
        },
        "createdDate": {
          "displayName": "Created Date",
          "invisible": true,
          "order": 8
        },
        "lastEditDate": {
          "displayName": "Last edit date",
          "invisible": true,
          "order": 12
        },
        "lastEditedBy": {
          "displayName": "Last edited by",
          "invisible": true,
          "order": 11
        },
        "layout": {
          "displayName": "Layout",
          "invisible": true,
          "order": 6
        },
        "name": {
          "displayName": "Name",
          "invisible": false,
          "order": 0
        },
        "nextEvents": {
          "displayName": "Next Events",
          "invisible": true,
          "order": 10
        },
        "owner": {
          "displayName": "Owner",
          "invisible": true,
          "order": 7
        },
        "part": {
          "displayName": "Part",
          "invisible": false,
          "order": 1
        },
        "quantity": {
          "displayName": "Quantity Per",
          "invisible": false,
          "order": 2
        },
        "quoteLine": {
          "displayName": "Quote Line",
          "invisible": false,
          "order": 13
        },
        "quoteNumber": {
          "displayName": "Quote Number",
          "invisible": true,
          "order": 15
        },
        "salesLine": {
          "displayName": "Sales Line",
          "invisible": true,
          "order": 14
        },
        "state": {
          "displayName": "State",
          "invisible": true,
          "order": 9
        },
        "total": {
          "displayName": "Total",
          "invisible": false,
          "order": 4
        },
        "uoM": {
          "displayName": "UoM",
          "invisible": false,
          "order": 5
        },
        "vendor": {
          "displayName": "Vendor",
          "invisible": true,
          "order": 16
        }
      },
      "readOnly": false,
      "recordCustomCode": "",
      "title": "import excel view"
    }
  },
  "viewsOrder": [
    "importexcelview"
  ]
}