{
  "displayColumn": "name",
  "isReactive": true,
  "meta": {
    "color": {
      "displayName": "Color",
      "invisible": true,
      "order": 11,
      "type": "string"
    },
    "createdDate": {
      "displayName": "Created Date",
      "invisible": true,
      "order": 3,
      "type": "date"
    },
    "description": {
      "displayName": "Description",
      "invisible": true,
      "order": 12,
      "type": "multiline_text"
    },
    "endDate": {
      "displayName": "End Date",
      "invisible": true,
      "order": 10,
      "type": "date"
    },
    "lastEditDate": {
      "displayName": "Last edit date",
      "invisible": true,
      "order": 7,
      "type": "date"
    },
    "lastEditedBy": {
      "displayName": "Last edited by",
      "invisible": true,
      "order": 6,
      "type": "user"
    },
    "layout": {
      "displayName": "Layout",
      "invisible": true,
      "order": 1,
      "type": "select"
    },
    "name": {
      "displayName": "Name",
      "order": 0,
      "type": "string"
    },
    "nextEvents": {
      "displayName": "Next Events",
      "invisible": true,
      "order": 5,
      "type": "string"
    },
    "opportunities_instance": {
      "dataGrid": "opportunities",
      "displayName": "Opportunities",
      "filterColumn": "project",
      "order": 15,
      "type": "datagrid"
    },
    "owner": {
      "displayName": "Owner",
      "invisible": true,
      "order": 2,
      "type": "user"
    },
    "progress": {
      "displayName": "Progress",
      "invisible": true,
      "order": 13,
      "type": "number"
    },
    "resource": {
      "displayName": "Resource",
      "invisible": true,
      "order": 14,
      "type": "string"
    },
    "startDate": {
      "displayName": "Start Date",
      "invisible": true,
      "order": 9,
      "type": "date"
    },
    "state": {
      "displayName": "State",
      "invisible": true,
      "order": 4,
      "type": "string"
    },
    "supportHub": {
      "displayName": "Support Hub",
      "indexed": true,
      "invisible": true,
      "lookUpTable": "onboardingQuestionaire",
      "order": 16,
      "type": "lookup"
    },
    "workOrderOperations_instance": {
      "dataGrid": "workOrderOperations",
      "displayName": "Work Order Operations",
      "filterColumn": "project",
      "order": 8,
      "type": "datagrid"
    }
  },
  "rowEditorFieldsForm": {
    "sections": [
      {
        "name": "section_394091",
        "label": "Projects",
        "clientKey": "section_394091",
        "order": 0,
        "rows": [
          {
            "name": "section_394091_row_771727",
            "label": "",
            "order": 0,
            "controls": [
              {
                "type": "text",
                "name": "control_95f67130-8273-11ee-adcf-a56ed5716b4d",
                "fieldName": "control_95f67130-8273-11ee-adcf-a56ed5716b4d",
                "label": "Name",
                "order": 0,
                "defaultValue": "",
                "value": "",
                "className": "col-md-6",
                "readonly": false,
                "readonlyCondition": "",
                "placeholder": "",
                "required": false,
                "requiredCondition": "",
                "isMultiLine": false,
                "isInteger": false,
                "decimalPlace": 0,
                "isTodayValue": false,
                "isTodayValueCreated": true,
                "dateFormat": "mm/dd/yy hh:mm p",
                "timezone": null,
                "selectedDataGrid": null,
                "printedFileName": null,
                "buttonLabel": "",
                "dataForTemplate": null,
                "selectedOutputDataGrid": null,
                "templateRowKey": null,
                "isForDownload": false,
                "attachRecord": false,
                "isCurrentUser": false,
                "isCurrentUserOwner": true,
                "isNowTimeValue": false,
                "timeFormat": "HH:mm",
                "isMultiple": false,
                "isAjax": false,
                "dataOptions": [],
                "ajaxDataUrl": "",
                "isChecked": false,
                "vif": "",
                "customCode": "",
                "invisible": false,
                "invisibleCondition": "",
                "invisibleLabel": false,
                "enableCustomValidation": false,
                "customValidationRule": "",
                "customValidationErrorMessage": "",
                "mask": "",
                "lookupOpenInModalDisabled": false,
                "editorMode": "javascript",
                "dataGridAvailableViews": [],
                "dataGridView": null,
                "dataGridAddRecordsText": "",
                "dataGridAddRecordText": "",
                "skipCrop": false,
                "disableRoundedStyle": false,
                "propName": "name"
              },
              {
                "type": "datepicker",
                "name": "control_de12e9f0-cff6-11ee-88b4-b999e885e16c",
                "fieldName": "control_de12e9f0-cff6-11ee-88b4-b999e885e16c",
                "label": "Start Date",
                "order": 0,
                "defaultValue": "",
                "value": "",
                "className": "col-md-6",
                "readonly": false,
                "readonlyCondition": "",
                "placeholder": "",
                "required": false,
                "requiredCondition": "",
                "isMultiLine": false,
                "isInteger": false,
                "decimalPlace": 2,
                "expression": "",
                "isTodayValue": false,
                "isTodayValueCreated": true,
                "dateFormat": "mm/dd/yy hh:mm p",
                "timezone": null,
                "selectedDataGrid": null,
                "printedFileName": null,
                "buttonLabel": "",
                "dataForTemplate": null,
                "selectedOutputDataGrid": null,
                "templateRowKey": null,
                "isForDownload": false,
                "openInNewTab": false,
                "attachRecord": false,
                "isCurrentUser": false,
                "isCurrentUserOwner": true,
                "isNowTimeValue": false,
                "timeFormat": "HH:mm",
                "isMultiple": false,
                "isAjax": false,
                "dataOptions": [],
                "ajaxDataUrl": "",
                "isChecked": false,
                "vif": "",
                "customCode": "",
                "invisible": false,
                "invisibleCondition": "",
                "invisibleLabel": false,
                "enableCustomValidation": false,
                "customValidationRule": "",
                "customValidationErrorMessage": "",
                "mask": "",
                "lookupOpenInModalDisabled": false,
                "editorMode": "javascript",
                "dataGridAvailableViews": [],
                "dataGridView": null,
                "dataGridAddRecordsText": "",
                "dataGridAddRecordText": "",
                "skipCrop": false,
                "disableRoundedStyle": false,
                "propName": "startDate",
                "gridId": "projects"
              },
              {
                "type": "datepicker",
                "name": "control_7193fde0-cff7-11ee-88b4-b999e885e16c",
                "fieldName": "control_7193fde0-cff7-11ee-88b4-b999e885e16c",
                "label": "End Date",
                "order": 0,
                "defaultValue": "",
                "value": "",
                "className": "col-md-6",
                "readonly": false,
                "readonlyCondition": "",
                "placeholder": "",
                "required": false,
                "requiredCondition": "",
                "isMultiLine": false,
                "isInteger": false,
                "decimalPlace": 2,
                "expression": "",
                "isTodayValue": false,
                "isTodayValueCreated": true,
                "dateFormat": "mm/dd/yy hh:mm p",
                "timezone": null,
                "selectedDataGrid": null,
                "printedFileName": null,
                "buttonLabel": "",
                "dataForTemplate": null,
                "selectedOutputDataGrid": null,
                "templateRowKey": null,
                "isForDownload": false,
                "openInNewTab": false,
                "attachRecord": false,
                "isCurrentUser": false,
                "isCurrentUserOwner": true,
                "isNowTimeValue": false,
                "timeFormat": "HH:mm",
                "isMultiple": false,
                "isAjax": false,
                "dataOptions": [],
                "ajaxDataUrl": "",
                "isChecked": false,
                "vif": "",
                "customCode": "",
                "invisible": false,
                "invisibleCondition": "",
                "invisibleLabel": false,
                "enableCustomValidation": false,
                "customValidationRule": "",
                "customValidationErrorMessage": "",
                "mask": "",
                "lookupOpenInModalDisabled": false,
                "editorMode": "javascript",
                "dataGridAvailableViews": [],
                "dataGridView": null,
                "dataGridAddRecordsText": "",
                "dataGridAddRecordText": "",
                "skipCrop": false,
                "disableRoundedStyle": false,
                "propName": "endDate",
                "gridId": "projects"
              },
              {
                "type": "user",
                "name": "control_962681e0-8273-11ee-adcf-a56ed5716b4d",
                "fieldName": "control_962681e0-8273-11ee-adcf-a56ed5716b4d",
                "label": "Owner",
                "order": 0,
                "defaultValue": "",
                "value": "",
                "className": "col-md-6",
                "readonly": false,
                "readonlyCondition": "",
                "placeholder": "",
                "required": false,
                "requiredCondition": "",
                "isMultiLine": false,
                "isInteger": false,
                "decimalPlace": 0,
                "isTodayValue": false,
                "isTodayValueCreated": true,
                "dateFormat": "mm/dd/yy hh:mm p",
                "timezone": null,
                "selectedDataGrid": null,
                "printedFileName": null,
                "buttonLabel": "",
                "dataForTemplate": null,
                "selectedOutputDataGrid": null,
                "templateRowKey": null,
                "isForDownload": false,
                "attachRecord": false,
                "isCurrentUser": false,
                "isCurrentUserOwner": true,
                "isNowTimeValue": false,
                "timeFormat": "HH:mm",
                "isMultiple": false,
                "isAjax": false,
                "dataOptions": [],
                "ajaxDataUrl": "",
                "isChecked": false,
                "vif": "",
                "customCode": "",
                "invisible": false,
                "invisibleCondition": "",
                "invisibleLabel": false,
                "enableCustomValidation": false,
                "customValidationRule": "",
                "customValidationErrorMessage": "",
                "mask": "",
                "lookupOpenInModalDisabled": false,
                "editorMode": "javascript",
                "dataGridAvailableViews": [],
                "dataGridView": null,
                "dataGridAddRecordsText": "",
                "dataGridAddRecordText": "",
                "skipCrop": false,
                "disableRoundedStyle": false,
                "propName": "owner",
                "gridId": "projects"
              },
              {
                "type": "text",
                "name": "control_8deaef80-cff7-11ee-88b4-b999e885e16c",
                "fieldName": "control_8deaef80-cff7-11ee-88b4-b999e885e16c",
                "label": "Color",
                "order": 0,
                "defaultValue": "",
                "value": "",
                "className": "col-md-6",
                "readonly": false,
                "readonlyCondition": "",
                "placeholder": "",
                "required": false,
                "requiredCondition": "",
                "isMultiLine": false,
                "isInteger": false,
                "decimalPlace": 2,
                "expression": "",
                "isTodayValue": false,
                "isTodayValueCreated": true,
                "dateFormat": "mm/dd/yy hh:mm p",
                "timezone": null,
                "selectedDataGrid": null,
                "printedFileName": null,
                "buttonLabel": "",
                "dataForTemplate": null,
                "selectedOutputDataGrid": null,
                "templateRowKey": null,
                "isForDownload": false,
                "openInNewTab": false,
                "attachRecord": false,
                "isCurrentUser": false,
                "isCurrentUserOwner": true,
                "isNowTimeValue": false,
                "timeFormat": "HH:mm",
                "isMultiple": false,
                "isAjax": false,
                "dataOptions": [],
                "ajaxDataUrl": "",
                "isChecked": false,
                "vif": "",
                "customCode": "",
                "invisible": false,
                "invisibleCondition": "",
                "invisibleLabel": false,
                "enableCustomValidation": false,
                "customValidationRule": "",
                "customValidationErrorMessage": "",
                "mask": "",
                "lookupOpenInModalDisabled": false,
                "editorMode": "javascript",
                "dataGridAvailableViews": [],
                "dataGridView": null,
                "dataGridAddRecordsText": "",
                "dataGridAddRecordText": "",
                "skipCrop": false,
                "disableRoundedStyle": false,
                "propName": "color"
              },
              {
                "type": "multiline_text",
                "name": "control_940ce990-cff7-11ee-88b4-b999e885e16c",
                "fieldName": "control_940ce990-cff7-11ee-88b4-b999e885e16c",
                "label": "Description",
                "order": 0,
                "defaultValue": "",
                "value": "",
                "className": "col-md-6",
                "readonly": false,
                "readonlyCondition": "",
                "placeholder": "",
                "required": false,
                "requiredCondition": "",
                "isMultiLine": false,
                "isInteger": false,
                "decimalPlace": 2,
                "expression": "",
                "isTodayValue": false,
                "isTodayValueCreated": true,
                "dateFormat": "mm/dd/yy hh:mm p",
                "timezone": null,
                "selectedDataGrid": null,
                "printedFileName": null,
                "buttonLabel": "",
                "dataForTemplate": null,
                "selectedOutputDataGrid": null,
                "templateRowKey": null,
                "isForDownload": false,
                "openInNewTab": false,
                "attachRecord": false,
                "isCurrentUser": false,
                "isCurrentUserOwner": true,
                "isNowTimeValue": false,
                "timeFormat": "HH:mm",
                "isMultiple": false,
                "isAjax": false,
                "dataOptions": [],
                "ajaxDataUrl": "",
                "isChecked": false,
                "vif": "",
                "customCode": "",
                "invisible": false,
                "invisibleCondition": "",
                "invisibleLabel": false,
                "enableCustomValidation": false,
                "customValidationRule": "",
                "customValidationErrorMessage": "",
                "mask": "",
                "lookupOpenInModalDisabled": false,
                "editorMode": "javascript",
                "dataGridAvailableViews": [],
                "dataGridView": null,
                "dataGridAddRecordsText": "",
                "dataGridAddRecordText": "",
                "skipCrop": false,
                "disableRoundedStyle": false,
                "propName": "description"
              },
              {
                "type": "number",
                "name": "control_9f72d9c0-cff7-11ee-88b4-b999e885e16c",
                "fieldName": "control_9f72d9c0-cff7-11ee-88b4-b999e885e16c",
                "label": "Progress",
                "order": 0,
                "defaultValue": "",
                "value": "",
                "className": "col-md-6",
                "readonly": false,
                "readonlyCondition": "",
                "placeholder": "",
                "required": false,
                "requiredCondition": "",
                "isMultiLine": false,
                "isInteger": false,
                "decimalPlace": 2,
                "expression": "",
                "isTodayValue": false,
                "isTodayValueCreated": true,
                "dateFormat": "mm/dd/yy hh:mm p",
                "timezone": null,
                "selectedDataGrid": null,
                "printedFileName": null,
                "buttonLabel": "",
                "dataForTemplate": null,
                "selectedOutputDataGrid": null,
                "templateRowKey": null,
                "isForDownload": false,
                "openInNewTab": false,
                "attachRecord": false,
                "isCurrentUser": false,
                "isCurrentUserOwner": true,
                "isNowTimeValue": false,
                "timeFormat": "HH:mm",
                "isMultiple": false,
                "isAjax": false,
                "dataOptions": [],
                "ajaxDataUrl": "",
                "isChecked": false,
                "vif": "",
                "customCode": "",
                "invisible": false,
                "invisibleCondition": "",
                "invisibleLabel": false,
                "enableCustomValidation": false,
                "customValidationRule": "",
                "customValidationErrorMessage": "",
                "mask": "",
                "lookupOpenInModalDisabled": false,
                "editorMode": "javascript",
                "dataGridAvailableViews": [],
                "dataGridView": null,
                "dataGridAddRecordsText": "",
                "dataGridAddRecordText": "",
                "skipCrop": false,
                "disableRoundedStyle": false,
                "propName": "progress"
              },
              {
                "type": "text",
                "name": "control_7bf1b060-cff8-11ee-88b4-b999e885e16c",
                "fieldName": "control_7bf1b060-cff8-11ee-88b4-b999e885e16c",
                "label": "Resource",
                "order": 0,
                "defaultValue": "",
                "value": "",
                "className": "col-md-6",
                "readonly": false,
                "readonlyCondition": "",
                "placeholder": "",
                "required": false,
                "requiredCondition": "",
                "isMultiLine": false,
                "isInteger": false,
                "decimalPlace": 2,
                "expression": "",
                "isTodayValue": false,
                "isTodayValueCreated": true,
                "dateFormat": "mm/dd/yy hh:mm p",
                "timezone": null,
                "selectedDataGrid": null,
                "printedFileName": null,
                "buttonLabel": "",
                "dataForTemplate": null,
                "selectedOutputDataGrid": null,
                "templateRowKey": null,
                "isForDownload": false,
                "openInNewTab": false,
                "attachRecord": false,
                "isCurrentUser": false,
                "isCurrentUserOwner": true,
                "isNowTimeValue": false,
                "timeFormat": "HH:mm",
                "isMultiple": false,
                "isAjax": false,
                "dataOptions": [],
                "ajaxDataUrl": "",
                "isChecked": false,
                "vif": "",
                "customCode": "",
                "invisible": false,
                "invisibleCondition": "",
                "invisibleLabel": false,
                "enableCustomValidation": false,
                "customValidationRule": "",
                "customValidationErrorMessage": "",
                "mask": "",
                "lookupOpenInModalDisabled": false,
                "editorMode": "javascript",
                "dataGridAvailableViews": [],
                "dataGridView": null,
                "dataGridAddRecordsText": "",
                "dataGridAddRecordText": "",
                "skipCrop": false,
                "disableRoundedStyle": false,
                "propName": "resource"
              },
              {
                "type": "lookup",
                "name": "control_e6ba7670-da60-11ef-a9e7-9da221c6925f",
                "fieldName": "control_e6ba7670-da60-11ef-a9e7-9da221c6925f",
                "label": "Support Hub",
                "order": 0,
                "defaultValue": "",
                "value": "",
                "className": "col-md-6",
                "readonly": false,
                "readonlyCondition": "",
                "placeholder": "",
                "required": false,
                "requiredCondition": "",
                "isMultiLine": false,
                "isInteger": false,
                "decimalPlace": 2,
                "expression": "",
                "oneDriveFileId": null,
                "isTodayValue": false,
                "isTodayValueCreated": true,
                "dateFormat": "mm/dd/yy hh:mm p",
                "timezone": null,
                "selectedDataGrid": null,
                "printedFileName": null,
                "buttonLabel": "",
                "dataForTemplate": null,
                "selectedOutputDataGrid": null,
                "templateRowKey": null,
                "isForDownload": false,
                "isOneDriveTemplate": false,
                "selectedOneDriveFile": null,
                "openInNewTab": false,
                "attachRecord": false,
                "isCurrentUser": false,
                "isCurrentUserOwner": true,
                "isNowTimeValue": false,
                "timeFormat": "HH:mm",
                "isMultiple": false,
                "isAjax": false,
                "dataOptions": [],
                "ajaxDataUrl": "",
                "isChecked": false,
                "vif": "",
                "customCode": "",
                "invisible": false,
                "invisibleCondition": "",
                "invisibleLabel": false,
                "enableCustomValidation": false,
                "customValidationRule": "",
                "customValidationErrorMessage": "",
                "mask": "",
                "lookupOpenInModalDisabled": false,
                "lookUpSearch": null,
                "editorMode": "javascript",
                "dataGridAvailableViews": [],
                "dataGridView": null,
                "dataGridAddRecordsText": "",
                "dataGridAddRecordText": "",
                "skipCrop": false,
                "disableRoundedStyle": false,
                "propName": "supportHub",
                "ableToAddLookUpVal": true
              },
              {
                "type": "datagrid",
                "name": "control_9b1f7100-d590-11ee-8866-578b39ad3d7d",
                "fieldName": "control_9b1f7100-d590-11ee-8866-578b39ad3d7d",
                "label": "Opportunities",
                "order": 0,
                "defaultValue": "",
                "value": "",
                "className": "col-md-12",
                "readonly": false,
                "readonlyCondition": "",
                "placeholder": "",
                "required": false,
                "requiredCondition": "",
                "isMultiLine": false,
                "isInteger": false,
                "decimalPlace": 2,
                "expression": "",
                "isTodayValue": false,
                "isTodayValueCreated": true,
                "dateFormat": "mm/dd/yy hh:mm p",
                "timezone": null,
                "selectedDataGrid": null,
                "printedFileName": null,
                "buttonLabel": "",
                "dataForTemplate": null,
                "selectedOutputDataGrid": null,
                "templateRowKey": null,
                "isForDownload": false,
                "openInNewTab": false,
                "attachRecord": false,
                "isCurrentUser": false,
                "isCurrentUserOwner": true,
                "isNowTimeValue": false,
                "timeFormat": "HH:mm",
                "isMultiple": false,
                "isAjax": false,
                "dataOptions": [],
                "ajaxDataUrl": "",
                "isChecked": false,
                "vif": "",
                "customCode": "",
                "invisible": false,
                "invisibleCondition": "",
                "invisibleLabel": false,
                "enableCustomValidation": false,
                "customValidationRule": "",
                "customValidationErrorMessage": "",
                "mask": "",
                "lookupOpenInModalDisabled": false,
                "editorMode": "javascript",
                "dataGridAvailableViews": [],
                "dataGridView": null,
                "dataGridAddRecordsText": "",
                "dataGridAddRecordText": "",
                "skipCrop": false,
                "disableRoundedStyle": false,
                "propName": "opportunities_instance"
              }
            ]
          }
        ],
        "labelPosition": "top",
        "isDynamic": false,
        "minInstance": 1,
        "maxInstance": 0,
        "instances": []
      },
      {
        "cleintKey": "hidden_section_95f64a20-8273-11ee-adcf-a56ed5716b4d",
        "instances": [],
        "isDynamic": false,
        "label": "Hidden Section",
        "vif": "false",
        "name": "hidden_section_95f64a20-8273-11ee-adcf-a56ed5716b4d",
        "order": 1,
        "rows": [
          {
            "name": "hidden_section_95f64a20-8273-11ee-adcf-a56ed5716b4d_row_95f64a21-8273-11ee-adcf-a56ed5716b4d",
            "controls": [
              {
                "type": "select",
                "name": "control_960f7770-8273-11ee-adcf-a56ed5716b4d",
                "fieldName": "control_960f7770-8273-11ee-adcf-a56ed5716b4d",
                "label": "Layout",
                "order": 0,
                "defaultValue": "",
                "value": "",
                "className": "col-md-6",
                "readonly": false,
                "readonlyCondition": "",
                "placeholder": "",
                "required": false,
                "requiredCondition": "",
                "isMultiLine": false,
                "isInteger": false,
                "decimalPlace": 0,
                "isTodayValue": false,
                "isTodayValueCreated": true,
                "dateFormat": "mm/dd/yy hh:mm p",
                "timezone": null,
                "selectedDataGrid": null,
                "printedFileName": null,
                "buttonLabel": "",
                "dataForTemplate": null,
                "selectedOutputDataGrid": null,
                "templateRowKey": null,
                "isForDownload": false,
                "attachRecord": false,
                "isCurrentUser": false,
                "isCurrentUserOwner": true,
                "isNowTimeValue": false,
                "timeFormat": "HH:mm",
                "isMultiple": false,
                "isAjax": false,
                "dataOptions": [],
                "ajaxDataUrl": "",
                "isChecked": false,
                "vif": "",
                "customCode": "",
                "invisible": true,
                "invisibleCondition": "",
                "invisibleLabel": false,
                "enableCustomValidation": false,
                "customValidationRule": "",
                "customValidationErrorMessage": "",
                "mask": "",
                "lookupOpenInModalDisabled": false,
                "editorMode": "javascript",
                "dataGridAvailableViews": [],
                "dataGridView": null,
                "dataGridAddRecordsText": "",
                "dataGridAddRecordText": "",
                "skipCrop": false,
                "disableRoundedStyle": false,
                "propName": "layout"
              },
              {
                "type": "datepicker",
                "name": "control_963f12f0-8273-11ee-adcf-a56ed5716b4d",
                "fieldName": "control_963f12f0-8273-11ee-adcf-a56ed5716b4d",
                "label": "Created Date",
                "order": 0,
                "defaultValue": "",
                "value": "",
                "className": "col-md-6",
                "readonly": false,
                "readonlyCondition": "",
                "placeholder": "",
                "required": false,
                "requiredCondition": "",
                "isMultiLine": false,
                "isInteger": false,
                "decimalPlace": 0,
                "isTodayValue": false,
                "isTodayValueCreated": true,
                "dateFormat": "mm/dd/yy hh:mm p",
                "timezone": null,
                "selectedDataGrid": null,
                "printedFileName": null,
                "buttonLabel": "",
                "dataForTemplate": null,
                "selectedOutputDataGrid": null,
                "templateRowKey": null,
                "isForDownload": false,
                "attachRecord": false,
                "isCurrentUser": false,
                "isCurrentUserOwner": true,
                "isNowTimeValue": false,
                "timeFormat": "HH:mm",
                "isMultiple": false,
                "isAjax": false,
                "dataOptions": [],
                "ajaxDataUrl": "",
                "isChecked": false,
                "vif": "",
                "customCode": "",
                "invisible": true,
                "invisibleCondition": "",
                "invisibleLabel": false,
                "enableCustomValidation": false,
                "customValidationRule": "",
                "customValidationErrorMessage": "",
                "mask": "",
                "lookupOpenInModalDisabled": false,
                "editorMode": "javascript",
                "dataGridAvailableViews": [],
                "dataGridView": null,
                "dataGridAddRecordsText": "",
                "dataGridAddRecordText": "",
                "skipCrop": false,
                "disableRoundedStyle": false,
                "propName": "createdDate"
              },
              {
                "type": "text",
                "name": "control_9653d370-8273-11ee-adcf-a56ed5716b4d",
                "fieldName": "control_9653d370-8273-11ee-adcf-a56ed5716b4d",
                "label": "State",
                "order": 0,
                "defaultValue": "",
                "value": "",
                "className": "col-md-6",
                "readonly": false,
                "readonlyCondition": "",
                "placeholder": "",
                "required": false,
                "requiredCondition": "",
                "isMultiLine": false,
                "isInteger": false,
                "decimalPlace": 0,
                "isTodayValue": false,
                "isTodayValueCreated": true,
                "dateFormat": "mm/dd/yy hh:mm p",
                "timezone": null,
                "selectedDataGrid": null,
                "printedFileName": null,
                "buttonLabel": "",
                "dataForTemplate": null,
                "selectedOutputDataGrid": null,
                "templateRowKey": null,
                "isForDownload": false,
                "attachRecord": false,
                "isCurrentUser": false,
                "isCurrentUserOwner": true,
                "isNowTimeValue": false,
                "timeFormat": "HH:mm",
                "isMultiple": false,
                "isAjax": false,
                "dataOptions": [],
                "ajaxDataUrl": "",
                "isChecked": false,
                "vif": "",
                "customCode": "",
                "invisible": true,
                "invisibleCondition": "",
                "invisibleLabel": false,
                "enableCustomValidation": false,
                "customValidationRule": "",
                "customValidationErrorMessage": "",
                "mask": "",
                "lookupOpenInModalDisabled": false,
                "editorMode": "javascript",
                "dataGridAvailableViews": [],
                "dataGridView": null,
                "dataGridAddRecordsText": "",
                "dataGridAddRecordText": "",
                "skipCrop": false,
                "disableRoundedStyle": false,
                "propName": "state"
              },
              {
                "type": "text",
                "name": "control_966893f0-8273-11ee-adcf-a56ed5716b4d",
                "fieldName": "control_966893f0-8273-11ee-adcf-a56ed5716b4d",
                "label": "Next Events",
                "order": 0,
                "defaultValue": "",
                "value": "",
                "className": "col-md-6",
                "readonly": false,
                "readonlyCondition": "",
                "placeholder": "",
                "required": false,
                "requiredCondition": "",
                "isMultiLine": false,
                "isInteger": false,
                "decimalPlace": 0,
                "isTodayValue": false,
                "isTodayValueCreated": true,
                "dateFormat": "mm/dd/yy hh:mm p",
                "timezone": null,
                "selectedDataGrid": null,
                "printedFileName": null,
                "buttonLabel": "",
                "dataForTemplate": null,
                "selectedOutputDataGrid": null,
                "templateRowKey": null,
                "isForDownload": false,
                "attachRecord": false,
                "isCurrentUser": false,
                "isCurrentUserOwner": true,
                "isNowTimeValue": false,
                "timeFormat": "HH:mm",
                "isMultiple": false,
                "isAjax": false,
                "dataOptions": [],
                "ajaxDataUrl": "",
                "isChecked": false,
                "vif": "",
                "customCode": "",
                "invisible": true,
                "invisibleCondition": "",
                "invisibleLabel": false,
                "enableCustomValidation": false,
                "customValidationRule": "",
                "customValidationErrorMessage": "",
                "mask": "",
                "lookupOpenInModalDisabled": false,
                "editorMode": "javascript",
                "dataGridAvailableViews": [],
                "dataGridView": null,
                "dataGridAddRecordsText": "",
                "dataGridAddRecordText": "",
                "skipCrop": false,
                "disableRoundedStyle": false,
                "propName": "nextEvents"
              },
              {
                "type": "user",
                "name": "control_967b3190-8273-11ee-adcf-a56ed5716b4d",
                "fieldName": "control_967b3190-8273-11ee-adcf-a56ed5716b4d",
                "label": "Last edited by",
                "order": 0,
                "defaultValue": "",
                "value": "",
                "className": "col-md-6",
                "readonly": true,
                "readonlyCondition": "",
                "placeholder": "",
                "required": false,
                "requiredCondition": "",
                "isMultiLine": false,
                "isInteger": false,
                "decimalPlace": 0,
                "isTodayValue": false,
                "isTodayValueCreated": true,
                "dateFormat": "mm/dd/yy hh:mm p",
                "timezone": null,
                "selectedDataGrid": null,
                "printedFileName": null,
                "buttonLabel": "",
                "dataForTemplate": null,
                "selectedOutputDataGrid": null,
                "templateRowKey": null,
                "isForDownload": false,
                "attachRecord": false,
                "isCurrentUser": false,
                "isCurrentUserOwner": true,
                "isNowTimeValue": false,
                "timeFormat": "HH:mm",
                "isMultiple": false,
                "isAjax": false,
                "dataOptions": [],
                "ajaxDataUrl": "",
                "isChecked": false,
                "vif": "",
                "customCode": "",
                "invisible": true,
                "invisibleCondition": "",
                "invisibleLabel": false,
                "enableCustomValidation": false,
                "customValidationRule": "",
                "customValidationErrorMessage": "",
                "mask": "",
                "lookupOpenInModalDisabled": false,
                "editorMode": "javascript",
                "dataGridAvailableViews": [],
                "dataGridView": null,
                "dataGridAddRecordsText": "",
                "dataGridAddRecordText": "",
                "skipCrop": false,
                "disableRoundedStyle": false,
                "propName": "lastEditedBy"
              },
              {
                "type": "datepicker",
                "name": "control_968ee0a0-8273-11ee-adcf-a56ed5716b4d",
                "fieldName": "control_968ee0a0-8273-11ee-adcf-a56ed5716b4d",
                "label": "Last edit date",
                "order": 0,
                "defaultValue": "",
                "value": "",
                "className": "col-md-6",
                "readonly": true,
                "readonlyCondition": "",
                "placeholder": "",
                "required": false,
                "requiredCondition": "",
                "isMultiLine": false,
                "isInteger": false,
                "decimalPlace": 0,
                "isTodayValue": false,
                "isTodayValueCreated": true,
                "dateFormat": "mm/dd/yy hh:mm p",
                "timezone": null,
                "selectedDataGrid": null,
                "printedFileName": null,
                "buttonLabel": "",
                "dataForTemplate": null,
                "selectedOutputDataGrid": null,
                "templateRowKey": null,
                "isForDownload": false,
                "attachRecord": false,
                "isCurrentUser": false,
                "isCurrentUserOwner": true,
                "isNowTimeValue": false,
                "timeFormat": "HH:mm",
                "isMultiple": false,
                "isAjax": false,
                "dataOptions": [],
                "ajaxDataUrl": "",
                "isChecked": false,
                "vif": "",
                "customCode": "",
                "invisible": true,
                "invisibleCondition": "",
                "invisibleLabel": false,
                "enableCustomValidation": false,
                "customValidationRule": "",
                "customValidationErrorMessage": "",
                "mask": "",
                "lookupOpenInModalDisabled": false,
                "editorMode": "javascript",
                "dataGridAvailableViews": [],
                "dataGridView": null,
                "dataGridAddRecordsText": "",
                "dataGridAddRecordText": "",
                "skipCrop": false,
                "disableRoundedStyle": false,
                "propName": "lastEditDate"
              }
            ]
          }
        ]
      },
      {
        "name": "section_805449",
        "label": "Work Order Operations",
        "clientKey": "section_805449",
        "order": 0,
        "rows": [
          {
            "name": "section_805449_row_542213",
            "label": "",
            "order": 0,
            "controls": [
              {
                "type": "datagrid",
                "name": "control_be77b470-8273-11ee-adcf-a56ed5716b4d",
                "fieldName": "control_be77b470-8273-11ee-adcf-a56ed5716b4d",
                "label": "Work Order Operations",
                "order": 0,
                "defaultValue": "",
                "value": "",
                "className": "col-md-12",
                "readonly": false,
                "readonlyCondition": "",
                "placeholder": "",
                "required": false,
                "requiredCondition": "",
                "isMultiLine": false,
                "isInteger": false,
                "decimalPlace": 0,
                "isTodayValue": false,
                "isTodayValueCreated": true,
                "dateFormat": "mm/dd/yy hh:mm p",
                "timezone": null,
                "selectedDataGrid": null,
                "printedFileName": null,
                "buttonLabel": "",
                "dataForTemplate": null,
                "selectedOutputDataGrid": null,
                "templateRowKey": null,
                "isForDownload": false,
                "attachRecord": false,
                "isCurrentUser": false,
                "isCurrentUserOwner": true,
                "isNowTimeValue": false,
                "timeFormat": "HH:mm",
                "isMultiple": false,
                "isAjax": false,
                "dataOptions": [],
                "ajaxDataUrl": "",
                "isChecked": false,
                "vif": "",
                "customCode": "",
                "invisible": false,
                "invisibleCondition": "",
                "invisibleLabel": true,
                "enableCustomValidation": false,
                "customValidationRule": "",
                "customValidationErrorMessage": "",
                "mask": "",
                "lookupOpenInModalDisabled": false,
                "editorMode": "javascript",
                "dataGridAvailableViews": [],
                "dataGridView": null,
                "dataGridAddRecordsText": "",
                "dataGridAddRecordText": "",
                "skipCrop": false,
                "disableRoundedStyle": false,
                "propName": "workOrderOperations_instance",
                "gridId": "projects"
              }
            ]
          }
        ],
        "labelPosition": "top",
        "isDynamic": false,
        "minInstance": 1,
        "maxInstance": 0,
        "instances": [],
        "vif": "",
        "collapsedByDefault": false
      }
    ],
    "layout": "collapse"
  },
  "source": "projects",
  "storageType": "dashboard",
  "title": "Projects"
}