{
  "defaultSort": {
    "column": "_id",
    "direction": "desc"
  },
  "displayColumn": "name",
  "filterBuilder": "{\"condition\":\"AND\",\"rules\":[{\"andOr\":\"AND\",\"key\":\"resourceGroup\",\"operator\":\"in\",\"value\":null,\"name\":\"Resource Group\",\"expression\":false,\"hidden\":false},{\"andOr\":\"\",\"key\":\"name\",\"operator\":\"contains\",\"value\":null,\"name\":\"Name\",\"expression\":false,\"hidden\":false}]}",
  "isReactive": true,
  "meta": {
    "calendar": {
      "Width": "182px",
      "displayName": "Calendar",
      "invisible": false,
      "order": 8,
      "type": "string"
    },
    "capacity": {
      "displayName": "Capacity",
      "invisible": false,
      "order": 2,
      "type": "number"
    },
    "color": {
      "displayName": "Color",
      "invisible": false,
      "order": 7,
      "type": "string"
    },
    "createdDate": {
      "displayName": "Created Date",
      "invisible": true,
      "order": 11,
      "type": "date"
    },
    "cycle1": {
      "displayName": "Cycle1",
      "invisible": true,
      "order": 20,
      "type": "number"
    },
    "description": {
      "displayName": "Description",
      "invisible": false,
      "order": 4,
      "type": "string"
    },
    "efficiencyPercentage": {
      "displayName": "Efficiency Percentage",
      "invisible": true,
      "order": 23,
      "type": "number"
    },
    "lastEditDate": {
      "displayName": "Last edit date",
      "invisible": true,
      "order": 18,
      "type": "date"
    },
    "lastEditedBy": {
      "displayName": "Last edited by",
      "invisible": true,
      "order": 16,
      "type": "user"
    },
    "layout": {
      "displayName": "Layout",
      "invisible": true,
      "order": 9,
      "type": "select"
    },
    "machineRunTime_instance": {
      "dataGrid": "machineRunTime",
      "displayName": "Machine Run Time",
      "filterColumn": "machine",
      "order": 22,
      "type": "datagrid"
    },
    "methodOperation": {
      "dataGrid": "methodOperations",
      "displayName": "Method Operation",
      "filterColumn": "resource",
      "order": 14,
      "type": "datagrid"
    },
    "name": {
      "displayName": "Name",
      "invisible": false,
      "order": 1,
      "type": "string"
    },
    "nextEvents": {
      "displayName": "Next Events",
      "invisible": true,
      "order": 15,
      "type": "string"
    },
    "operationType": {
      "displayName": "Operation Type",
      "invisible": true,
      "lookUpTable": "operationTypes",
      "order": 19,
      "skipParse": true,
      "type": "lookup"
    },
    "opportunityLines_instance": {
      "dataGrid": "opportunityLines",
      "displayName": "Opportunity Lines",
      "filterColumn": "resource",
      "order": 17,
      "type": "datagrid"
    },
    "owner": {
      "displayName": "Owner",
      "invisible": true,
      "order": 10,
      "type": "user"
    },
    "resourceGroup": {
      "Width": "171px",
      "displayName": "Resource Group",
      "invisible": false,
      "lookUpTable": "resourceGroups",
      "order": 5,
      "type": "lookup"
    },
    "sequence": {
      "displayName": "Sequence",
      "invisible": false,
      "order": 0,
      "type": "string"
    },
    "setup1": {
      "displayName": "Setup1",
      "invisible": true,
      "order": 21,
      "type": "number"
    },
    "skillLevel": {
      "displayName": "Skill Level",
      "invisible": false,
      "order": 3,
      "type": "number"
    },
    "state": {
      "displayName": "State",
      "invisible": true,
      "order": 12,
      "type": "string"
    },
    "timeEntries_instance": {
      "dataGrid": "timeEntries",
      "displayName": "Time Entries",
      "filterColumn": "resource",
      "order": 13,
      "type": "datagrid"
    },
    "totalCostPerHour": {
      "Width": "215px",
      "displayName": "Total Cost Per Hour",
      "invisible": false,
      "order": 6,
      "priceFormat": true,
      "type": "number"
    }
  },
  "rowEditorFieldsForm": {
    "sections": [
      {
        "name": "section_242200",
        "label": "Resource",
        "clientKey": "section_242200",
        "order": 0,
        "rows": [
          {
            "name": "section_242200_row_32120",
            "label": "",
            "order": 0,
            "controls": [
              {
                "type": "text",
                "name": "control_82ad9442-5227-11ee-8eb0-6b93d594e479",
                "fieldName": "control_82ad9442-5227-11ee-8eb0-6b93d594e479",
                "label": "Name",
                "order": 0,
                "defaultValue": "",
                "value": "",
                "className": "col-md-6",
                "readonly": false,
                "readonlyCondition": "",
                "placeholder": "",
                "required": false,
                "requiredCondition": "",
                "isMultiLine": false,
                "isInteger": false,
                "decimalPlace": 0,
                "isTodayValue": false,
                "isTodayValueCreated": true,
                "dateFormat": "mm/dd/yy hh:mm p",
                "timezone": null,
                "selectedDataGrid": null,
                "printedFileName": null,
                "buttonLabel": "",
                "dataForTemplate": null,
                "selectedOutputDataGrid": null,
                "templateRowKey": null,
                "isForDownload": false,
                "attachRecord": false,
                "isCurrentUser": false,
                "isCurrentUserOwner": true,
                "isNowTimeValue": false,
                "timeFormat": "HH:mm",
                "isMultiple": false,
                "isAjax": false,
                "dataOptions": [],
                "ajaxDataUrl": "",
                "isChecked": false,
                "vif": "",
                "customCode": "",
                "invisible": false,
                "invisibleCondition": "",
                "invisibleInDataGrid": false,
                "invisibleLabel": false,
                "enableCustomValidation": false,
                "customValidationRule": "",
                "customValidationErrorMessage": "",
                "mask": "",
                "lookupOpenInModalDisabled": false,
                "editorMode": "javascript",
                "dataGridAvailableViews": [],
                "dataGridView": null,
                "dataGridAddRecordsText": "",
                "dataGridAddRecordText": "",
                "skipCrop": false,
                "disableRoundedStyle": false,
                "propName": "name"
              },
              {
                "type": "number",
                "name": "control_644e3a90-0e47-11ef-a189-7b8ec93a1855",
                "fieldName": "control_644e3a90-0e47-11ef-a189-7b8ec93a1855",
                "label": "Skill Level",
                "order": 0,
                "defaultValue": "",
                "value": "",
                "className": "col-md-6",
                "readonly": false,
                "readonlyCondition": "",
                "placeholder": "",
                "required": false,
                "requiredCondition": "",
                "isMultiLine": false,
                "isInteger": false,
                "decimalPlace": 2,
                "expression": "",
                "isTodayValue": false,
                "isTodayValueCreated": true,
                "dateFormat": "mm/dd/yy hh:mm p",
                "timezone": null,
                "selectedDataGrid": null,
                "printedFileName": null,
                "buttonLabel": "",
                "dataForTemplate": null,
                "selectedOutputDataGrid": null,
                "templateRowKey": null,
                "isForDownload": false,
                "openInNewTab": false,
                "attachRecord": false,
                "isCurrentUser": false,
                "isCurrentUserOwner": true,
                "isNowTimeValue": false,
                "timeFormat": "HH:mm",
                "isMultiple": false,
                "isAjax": false,
                "dataOptions": [],
                "ajaxDataUrl": "",
                "isChecked": false,
                "vif": "",
                "customCode": "",
                "invisible": false,
                "invisibleCondition": "",
                "invisibleLabel": false,
                "enableCustomValidation": false,
                "customValidationRule": "",
                "customValidationErrorMessage": "",
                "mask": "",
                "lookupOpenInModalDisabled": false,
                "lookUpSearch": null,
                "editorMode": "javascript",
                "dataGridAvailableViews": [],
                "dataGridView": null,
                "dataGridAddRecordsText": "",
                "dataGridAddRecordText": "",
                "skipCrop": false,
                "disableRoundedStyle": false,
                "propName": "skillLevel"
              },
              {
                "type": "text",
                "name": "control_56204a93-5267-11ee-9c2c-810c2126219e_",
                "fieldName": "control_56204a93-5267-11ee-9c2c-810c2126219e_",
                "label": "Calendar",
                "order": 0,
                "defaultValue": "",
                "value": "",
                "className": "col-md-6",
                "readonly": false,
                "required": false,
                "isMultiLine": false,
                "isInteger": false,
                "decimalPlace": 0,
                "isTodayValue": false,
                "dateFormat": "mm/dd/yy hh:mm p",
                "isNowTimeValue": false,
                "timeFormat": "HH:mm",
                "isMultiple": false,
                "isAjax": false,
                "dataOptions": [],
                "ajaxDataUrl": "",
                "isChecked": false,
                "vif": "",
                "customCode": "",
                "propName": "calendar",
                "gridId": "resources"
              },
              {
                "type": "number",
                "name": "control_f6e9a2c0-985a-11ef-8575-ddf98abfe38f",
                "fieldName": "control_f6e9a2c0-985a-11ef-8575-ddf98abfe38f",
                "label": "Efficiency Percentage",
                "order": 0,
                "defaultValue": "",
                "value": "",
                "className": "col-md-6",
                "readonly": false,
                "readonlyCondition": "",
                "placeholder": "",
                "required": false,
                "requiredCondition": "",
                "isMultiLine": false,
                "isInteger": false,
                "decimalPlace": 2,
                "expression": "",
                "oneDriveFileId": null,
                "isTodayValue": false,
                "isTodayValueCreated": true,
                "dateFormat": "mm/dd/yy hh:mm p",
                "timezone": null,
                "selectedDataGrid": null,
                "printedFileName": null,
                "buttonLabel": "",
                "dataForTemplate": null,
                "selectedOutputDataGrid": null,
                "templateRowKey": null,
                "isForDownload": false,
                "isOneDriveTemplate": false,
                "selectedOneDriveFile": null,
                "openInNewTab": false,
                "attachRecord": false,
                "isCurrentUser": false,
                "isCurrentUserOwner": true,
                "isNowTimeValue": false,
                "timeFormat": "HH:mm",
                "isMultiple": false,
                "isAjax": false,
                "dataOptions": [],
                "ajaxDataUrl": "",
                "isChecked": false,
                "vif": "",
                "customCode": "",
                "invisible": false,
                "invisibleCondition": "",
                "invisibleLabel": false,
                "enableCustomValidation": false,
                "customValidationRule": "",
                "customValidationErrorMessage": "",
                "mask": "",
                "lookupOpenInModalDisabled": false,
                "lookUpSearch": null,
                "editorMode": "javascript",
                "dataGridAvailableViews": [],
                "dataGridView": null,
                "dataGridAddRecordsText": "",
                "dataGridAddRecordText": "",
                "skipCrop": false,
                "disableRoundedStyle": false,
                "propName": "efficiencyPercentage"
              },
              {
                "type": "text",
                "name": "control_56204a95-5267-11ee-9c2c-810c2126219e_",
                "fieldName": "control_56204a95-5267-11ee-9c2c-810c2126219e_",
                "label": "Description",
                "order": 0,
                "defaultValue": "",
                "value": "",
                "className": "col-md-6",
                "readonly": false,
                "required": false,
                "isMultiLine": false,
                "isInteger": false,
                "decimalPlace": 0,
                "isTodayValue": false,
                "dateFormat": "mm/dd/yy hh:mm p",
                "isNowTimeValue": false,
                "timeFormat": "HH:mm",
                "isMultiple": false,
                "isAjax": false,
                "dataOptions": [],
                "ajaxDataUrl": "",
                "isChecked": false,
                "vif": "",
                "customCode": "",
                "propName": "description"
              },
              {
                "type": "lookup",
                "name": "control_56204aa3-5267-11ee-9c2c-810c2126219e_",
                "fieldName": "control_56204aa3-5267-11ee-9c2c-810c2126219e_",
                "label": "Operation Type",
                "order": 0,
                "defaultValue": "",
                "value": "",
                "className": "col-md-6",
                "readonly": false,
                "required": false,
                "isMultiLine": false,
                "isInteger": false,
                "decimalPlace": 0,
                "isTodayValue": false,
                "dateFormat": "mm/dd/yy hh:mm p",
                "isNowTimeValue": false,
                "timeFormat": "HH:mm",
                "isMultiple": false,
                "isAjax": false,
                "dataOptions": [],
                "ajaxDataUrl": "",
                "isChecked": false,
                "vif": "",
                "customCode": "",
                "propName": "operationType",
                "gridId": "resources",
                "lookUpTable": "operationTypes"
              },
              {
                "type": "lookup",
                "name": "control_56204aa7-5267-11ee-9c2c-810c2126219e_",
                "fieldName": "control_56204aa7-5267-11ee-9c2c-810c2126219e_",
                "label": "Resource Group",
                "order": 0,
                "defaultValue": "",
                "value": "",
                "className": "col-md-6",
                "readonly": false,
                "required": false,
                "isMultiLine": false,
                "isInteger": false,
                "decimalPlace": 0,
                "isTodayValue": false,
                "dateFormat": "mm/dd/yy hh:mm p",
                "isNowTimeValue": false,
                "timeFormat": "HH:mm",
                "isMultiple": false,
                "isAjax": false,
                "dataOptions": [],
                "ajaxDataUrl": "",
                "isChecked": false,
                "vif": "",
                "customCode": "",
                "propName": "resourceGroup",
                "gridId": "resources",
                "lookUpTable": "resourceGroups"
              },
              {
                "type": "number",
                "name": "control_56204aac-5267-11ee-9c2c-810c2126219e_",
                "fieldName": "control_56204aac-5267-11ee-9c2c-810c2126219e_",
                "label": "Total Cost Per Hour",
                "order": 0,
                "defaultValue": "",
                "value": "",
                "className": "col-md-6",
                "readonly": false,
                "required": false,
                "isMultiLine": false,
                "isInteger": false,
                "decimalPlace": 0,
                "isTodayValue": false,
                "dateFormat": "mm/dd/yy hh:mm p",
                "isNowTimeValue": false,
                "timeFormat": "HH:mm",
                "isMultiple": false,
                "isAjax": false,
                "dataOptions": [],
                "ajaxDataUrl": "",
                "isChecked": false,
                "vif": "",
                "customCode": "",
                "propName": "totalCostPerHour",
                "gridId": "resources"
              },
              {
                "type": "number",
                "name": "control_fe4359d0-0e3f-11ef-a189-7b8ec93a1855",
                "fieldName": "control_fe4359d0-0e3f-11ef-a189-7b8ec93a1855",
                "label": "Capacity",
                "order": 0,
                "defaultValue": "",
                "value": "",
                "className": "col-md-6",
                "readonly": false,
                "readonlyCondition": "",
                "placeholder": "",
                "required": false,
                "requiredCondition": "",
                "isMultiLine": false,
                "isInteger": false,
                "decimalPlace": 2,
                "expression": "",
                "isTodayValue": false,
                "isTodayValueCreated": true,
                "dateFormat": "mm/dd/yy hh:mm p",
                "timezone": null,
                "selectedDataGrid": null,
                "printedFileName": null,
                "buttonLabel": "",
                "dataForTemplate": null,
                "selectedOutputDataGrid": null,
                "templateRowKey": null,
                "isForDownload": false,
                "openInNewTab": false,
                "attachRecord": false,
                "isCurrentUser": false,
                "isCurrentUserOwner": true,
                "isNowTimeValue": false,
                "timeFormat": "HH:mm",
                "isMultiple": false,
                "isAjax": false,
                "dataOptions": [],
                "ajaxDataUrl": "",
                "isChecked": false,
                "vif": "",
                "customCode": "",
                "invisible": false,
                "invisibleCondition": "",
                "invisibleLabel": false,
                "enableCustomValidation": false,
                "customValidationRule": "",
                "customValidationErrorMessage": "",
                "mask": "",
                "lookupOpenInModalDisabled": false,
                "lookUpSearch": null,
                "editorMode": "javascript",
                "dataGridAvailableViews": [],
                "dataGridView": null,
                "dataGridAddRecordsText": "",
                "dataGridAddRecordText": "",
                "skipCrop": false,
                "disableRoundedStyle": false,
                "propName": "capacity",
                "gridId": "resources"
              },
              {
                "type": "text",
                "name": "control_baa0fc40-dbff-11ee-827c-9fb0ad5273bf",
                "fieldName": "control_baa0fc40-dbff-11ee-827c-9fb0ad5273bf",
                "label": "Sequence",
                "order": 0,
                "defaultValue": "",
                "value": "",
                "className": "col-md-6",
                "readonly": false,
                "readonlyCondition": "",
                "placeholder": "",
                "required": false,
                "requiredCondition": "",
                "isMultiLine": false,
                "isInteger": false,
                "decimalPlace": 2,
                "expression": "",
                "isTodayValue": false,
                "isTodayValueCreated": true,
                "dateFormat": "mm/dd/yy hh:mm p",
                "timezone": null,
                "selectedDataGrid": null,
                "printedFileName": null,
                "buttonLabel": "",
                "dataForTemplate": null,
                "selectedOutputDataGrid": null,
                "templateRowKey": null,
                "isForDownload": false,
                "openInNewTab": false,
                "attachRecord": false,
                "isCurrentUser": false,
                "isCurrentUserOwner": true,
                "isNowTimeValue": false,
                "timeFormat": "HH:mm",
                "isMultiple": false,
                "isAjax": false,
                "dataOptions": [],
                "ajaxDataUrl": "",
                "isChecked": false,
                "vif": "",
                "customCode": "",
                "invisible": false,
                "invisibleCondition": "",
                "invisibleLabel": false,
                "enableCustomValidation": false,
                "customValidationRule": "",
                "customValidationErrorMessage": "",
                "mask": "",
                "lookupOpenInModalDisabled": false,
                "editorMode": "javascript",
                "dataGridAvailableViews": [],
                "dataGridView": null,
                "dataGridAddRecordsText": "",
                "dataGridAddRecordText": "",
                "skipCrop": false,
                "disableRoundedStyle": false,
                "propName": "sequence"
              }
            ]
          }
        ],
        "labelPosition": "top",
        "isDynamic": false,
        "minInstance": 1,
        "maxInstance": 0,
        "instances": []
      },
      {
        "cleintKey": "hidden_section_82ad9440-5227-11ee-8eb0-6b93d594e479",
        "instances": [],
        "isDynamic": false,
        "label": "Hidden Section",
        "vif": "false",
        "name": "hidden_section_82ad9440-5227-11ee-8eb0-6b93d594e479",
        "order": 1,
        "rows": [
          {
            "name": "hidden_section_82ad9440-5227-11ee-8eb0-6b93d594e479_row_82ad9441-5227-11ee-8eb0-6b93d594e479",
            "controls": [
              {
                "type": "select",
                "name": "control_82cd0320-5227-11ee-8eb0-6b93d594e479",
                "fieldName": "control_82cd0320-5227-11ee-8eb0-6b93d594e479",
                "label": "Layout",
                "order": 0,
                "defaultValue": "",
                "value": "",
                "className": "col-md-6",
                "readonly": false,
                "readonlyCondition": "",
                "placeholder": "",
                "required": false,
                "requiredCondition": "",
                "isMultiLine": false,
                "isInteger": false,
                "decimalPlace": 0,
                "isTodayValue": false,
                "isTodayValueCreated": true,
                "dateFormat": "mm/dd/yy hh:mm p",
                "timezone": null,
                "selectedDataGrid": null,
                "printedFileName": null,
                "buttonLabel": "",
                "dataForTemplate": null,
                "selectedOutputDataGrid": null,
                "templateRowKey": null,
                "isForDownload": false,
                "attachRecord": false,
                "isCurrentUser": false,
                "isCurrentUserOwner": true,
                "isNowTimeValue": false,
                "timeFormat": "HH:mm",
                "isMultiple": false,
                "isAjax": false,
                "dataOptions": [],
                "ajaxDataUrl": "",
                "isChecked": false,
                "vif": "",
                "customCode": "",
                "invisible": true,
                "invisibleCondition": "",
                "invisibleInDataGrid": false,
                "invisibleLabel": false,
                "enableCustomValidation": false,
                "customValidationRule": "",
                "customValidationErrorMessage": "",
                "mask": "",
                "lookupOpenInModalDisabled": false,
                "editorMode": "javascript",
                "dataGridAvailableViews": [],
                "dataGridView": null,
                "dataGridAddRecordsText": "",
                "dataGridAddRecordText": "",
                "skipCrop": false,
                "disableRoundedStyle": false,
                "propName": "layout"
              },
              {
                "type": "text",
                "name": "control_3acdbe10-fb33-11ee-8154-3dc44b16e583",
                "fieldName": "control_3acdbe10-fb33-11ee-8154-3dc44b16e583",
                "label": "Color",
                "order": 0,
                "defaultValue": "",
                "value": "",
                "className": "col-md-6",
                "readonly": false,
                "readonlyCondition": "",
                "placeholder": "",
                "required": false,
                "requiredCondition": "",
                "isMultiLine": false,
                "isInteger": false,
                "decimalPlace": 2,
                "expression": "",
                "isTodayValue": false,
                "isTodayValueCreated": true,
                "dateFormat": "mm/dd/yy hh:mm p",
                "timezone": null,
                "selectedDataGrid": null,
                "printedFileName": null,
                "buttonLabel": "",
                "dataForTemplate": null,
                "selectedOutputDataGrid": null,
                "templateRowKey": null,
                "isForDownload": false,
                "openInNewTab": false,
                "attachRecord": false,
                "isCurrentUser": false,
                "isCurrentUserOwner": true,
                "isNowTimeValue": false,
                "timeFormat": "HH:mm",
                "isMultiple": false,
                "isAjax": false,
                "dataOptions": [],
                "ajaxDataUrl": "",
                "isChecked": false,
                "vif": "",
                "customCode": "",
                "invisible": false,
                "invisibleCondition": "",
                "invisibleLabel": false,
                "enableCustomValidation": false,
                "customValidationRule": "",
                "customValidationErrorMessage": "",
                "mask": "",
                "lookupOpenInModalDisabled": false,
                "editorMode": "javascript",
                "dataGridAvailableViews": [],
                "dataGridView": null,
                "dataGridAddRecordsText": "",
                "dataGridAddRecordText": "",
                "skipCrop": false,
                "disableRoundedStyle": false,
                "propName": "color",
                "gridId": "resources"
              },
              {
                "type": "number",
                "name": "control_3ddc0cc0-f0f1-11ee-a0f0-7feaedc6b4e5",
                "fieldName": "control_3ddc0cc0-f0f1-11ee-a0f0-7feaedc6b4e5",
                "label": "Cycle1",
                "order": 0,
                "defaultValue": "",
                "value": "",
                "className": "col-md-6",
                "readonly": false,
                "readonlyCondition": "",
                "placeholder": "",
                "required": false,
                "requiredCondition": "",
                "isMultiLine": false,
                "isInteger": false,
                "decimalPlace": 2,
                "expression": "",
                "isTodayValue": false,
                "isTodayValueCreated": true,
                "dateFormat": "mm/dd/yy hh:mm p",
                "timezone": null,
                "selectedDataGrid": null,
                "printedFileName": null,
                "buttonLabel": "",
                "dataForTemplate": null,
                "selectedOutputDataGrid": null,
                "templateRowKey": null,
                "isForDownload": false,
                "openInNewTab": false,
                "attachRecord": false,
                "isCurrentUser": false,
                "isCurrentUserOwner": true,
                "isNowTimeValue": false,
                "timeFormat": "HH:mm",
                "isMultiple": false,
                "isAjax": false,
                "dataOptions": [],
                "ajaxDataUrl": "",
                "isChecked": false,
                "vif": "",
                "customCode": "",
                "invisible": false,
                "invisibleCondition": "",
                "invisibleLabel": false,
                "enableCustomValidation": false,
                "customValidationRule": "",
                "customValidationErrorMessage": "",
                "mask": "",
                "lookupOpenInModalDisabled": false,
                "editorMode": "javascript",
                "dataGridAvailableViews": [],
                "dataGridView": null,
                "dataGridAddRecordsText": "",
                "dataGridAddRecordText": "",
                "skipCrop": false,
                "disableRoundedStyle": false,
                "propName": "cycle1",
                "gridId": "resources"
              },
              {
                "type": "datagrid",
                "name": "control_d30cb160-db38-11ee-b796-eb84c346f879",
                "fieldName": "control_d30cb160-db38-11ee-b796-eb84c346f879",
                "label": "Opportunity Lines",
                "order": 0,
                "defaultValue": "",
                "value": "",
                "className": "col-md-12",
                "readonly": false,
                "readonlyCondition": "",
                "placeholder": "",
                "required": false,
                "requiredCondition": "",
                "isMultiLine": false,
                "isInteger": false,
                "decimalPlace": 2,
                "expression": "",
                "isTodayValue": false,
                "isTodayValueCreated": true,
                "dateFormat": "mm/dd/yy hh:mm p",
                "timezone": null,
                "selectedDataGrid": null,
                "printedFileName": null,
                "buttonLabel": "",
                "dataForTemplate": null,
                "selectedOutputDataGrid": null,
                "templateRowKey": null,
                "isForDownload": false,
                "openInNewTab": false,
                "attachRecord": false,
                "isCurrentUser": false,
                "isCurrentUserOwner": true,
                "isNowTimeValue": false,
                "timeFormat": "HH:mm",
                "isMultiple": false,
                "isAjax": false,
                "dataOptions": [],
                "ajaxDataUrl": "",
                "isChecked": false,
                "vif": "",
                "customCode": "",
                "invisible": false,
                "invisibleCondition": "",
                "invisibleLabel": false,
                "enableCustomValidation": false,
                "customValidationRule": "",
                "customValidationErrorMessage": "",
                "mask": "",
                "lookupOpenInModalDisabled": false,
                "editorMode": "javascript",
                "dataGridAvailableViews": [],
                "dataGridView": null,
                "dataGridAddRecordsText": "",
                "dataGridAddRecordText": "",
                "skipCrop": false,
                "disableRoundedStyle": false,
                "propName": "opportunityLines_instance"
              },
              {
                "type": "user",
                "name": "control_82eebbf0-5227-11ee-8eb0-6b93d594e479",
                "fieldName": "control_82eebbf0-5227-11ee-8eb0-6b93d594e479",
                "label": "Owner",
                "order": 0,
                "defaultValue": "",
                "value": "",
                "className": "col-md-6",
                "readonly": false,
                "readonlyCondition": "",
                "placeholder": "",
                "required": false,
                "requiredCondition": "",
                "isMultiLine": false,
                "isInteger": false,
                "decimalPlace": 0,
                "isTodayValue": false,
                "isTodayValueCreated": true,
                "dateFormat": "mm/dd/yy hh:mm p",
                "timezone": null,
                "selectedDataGrid": null,
                "printedFileName": null,
                "buttonLabel": "",
                "dataForTemplate": null,
                "selectedOutputDataGrid": null,
                "templateRowKey": null,
                "isForDownload": false,
                "attachRecord": false,
                "isCurrentUser": false,
                "isCurrentUserOwner": true,
                "isNowTimeValue": false,
                "timeFormat": "HH:mm",
                "isMultiple": false,
                "isAjax": false,
                "dataOptions": [],
                "ajaxDataUrl": "",
                "isChecked": false,
                "vif": "",
                "customCode": "",
                "invisible": true,
                "invisibleCondition": "",
                "invisibleInDataGrid": false,
                "invisibleLabel": false,
                "enableCustomValidation": false,
                "customValidationRule": "",
                "customValidationErrorMessage": "",
                "mask": "",
                "lookupOpenInModalDisabled": false,
                "editorMode": "javascript",
                "dataGridAvailableViews": [],
                "dataGridView": null,
                "dataGridAddRecordsText": "",
                "dataGridAddRecordText": "",
                "skipCrop": false,
                "disableRoundedStyle": false,
                "propName": "owner"
              },
              {
                "type": "number",
                "name": "control_423ca7c0-f0f1-11ee-a0f0-7feaedc6b4e5",
                "fieldName": "control_423ca7c0-f0f1-11ee-a0f0-7feaedc6b4e5",
                "label": "Setup1",
                "order": 0,
                "defaultValue": "",
                "value": "",
                "className": "col-md-6",
                "readonly": false,
                "readonlyCondition": "",
                "placeholder": "",
                "required": false,
                "requiredCondition": "",
                "isMultiLine": false,
                "isInteger": false,
                "decimalPlace": 2,
                "expression": "",
                "isTodayValue": false,
                "isTodayValueCreated": true,
                "dateFormat": "mm/dd/yy hh:mm p",
                "timezone": null,
                "selectedDataGrid": null,
                "printedFileName": null,
                "buttonLabel": "",
                "dataForTemplate": null,
                "selectedOutputDataGrid": null,
                "templateRowKey": null,
                "isForDownload": false,
                "openInNewTab": false,
                "attachRecord": false,
                "isCurrentUser": false,
                "isCurrentUserOwner": true,
                "isNowTimeValue": false,
                "timeFormat": "HH:mm",
                "isMultiple": false,
                "isAjax": false,
                "dataOptions": [],
                "ajaxDataUrl": "",
                "isChecked": false,
                "vif": "",
                "customCode": "",
                "invisible": false,
                "invisibleCondition": "",
                "invisibleLabel": false,
                "enableCustomValidation": false,
                "customValidationRule": "",
                "customValidationErrorMessage": "",
                "mask": "",
                "lookupOpenInModalDisabled": false,
                "editorMode": "javascript",
                "dataGridAvailableViews": [],
                "dataGridView": null,
                "dataGridAddRecordsText": "",
                "dataGridAddRecordText": "",
                "skipCrop": false,
                "disableRoundedStyle": false,
                "propName": "setup1",
                "gridId": "resources"
              },
              {
                "type": "datepicker",
                "name": "control_830a3330-5227-11ee-8eb0-6b93d594e479",
                "fieldName": "control_830a3330-5227-11ee-8eb0-6b93d594e479",
                "label": "Created Date",
                "order": 0,
                "defaultValue": "",
                "value": "",
                "className": "col-md-6",
                "readonly": false,
                "readonlyCondition": "",
                "placeholder": "",
                "required": false,
                "requiredCondition": "",
                "isMultiLine": false,
                "isInteger": false,
                "decimalPlace": 0,
                "isTodayValue": false,
                "isTodayValueCreated": true,
                "dateFormat": "mm/dd/yy hh:mm p",
                "timezone": null,
                "selectedDataGrid": null,
                "printedFileName": null,
                "buttonLabel": "",
                "dataForTemplate": null,
                "selectedOutputDataGrid": null,
                "templateRowKey": null,
                "isForDownload": false,
                "attachRecord": false,
                "isCurrentUser": false,
                "isCurrentUserOwner": true,
                "isNowTimeValue": false,
                "timeFormat": "HH:mm",
                "isMultiple": false,
                "isAjax": false,
                "dataOptions": [],
                "ajaxDataUrl": "",
                "isChecked": false,
                "vif": "",
                "customCode": "",
                "invisible": true,
                "invisibleCondition": "",
                "invisibleInDataGrid": false,
                "invisibleLabel": false,
                "enableCustomValidation": false,
                "customValidationRule": "",
                "customValidationErrorMessage": "",
                "mask": "",
                "lookupOpenInModalDisabled": false,
                "editorMode": "javascript",
                "dataGridAvailableViews": [],
                "dataGridView": null,
                "dataGridAddRecordsText": "",
                "dataGridAddRecordText": "",
                "skipCrop": false,
                "disableRoundedStyle": false,
                "propName": "createdDate"
              },
              {
                "type": "text",
                "name": "control_8328b7b0-5227-11ee-8eb0-6b93d594e479",
                "fieldName": "control_8328b7b0-5227-11ee-8eb0-6b93d594e479",
                "label": "State",
                "order": 0,
                "defaultValue": "",
                "value": "",
                "className": "col-md-6",
                "readonly": false,
                "readonlyCondition": "",
                "placeholder": "",
                "required": false,
                "requiredCondition": "",
                "isMultiLine": false,
                "isInteger": false,
                "decimalPlace": 0,
                "isTodayValue": false,
                "isTodayValueCreated": true,
                "dateFormat": "mm/dd/yy hh:mm p",
                "timezone": null,
                "selectedDataGrid": null,
                "printedFileName": null,
                "buttonLabel": "",
                "dataForTemplate": null,
                "selectedOutputDataGrid": null,
                "templateRowKey": null,
                "isForDownload": false,
                "attachRecord": false,
                "isCurrentUser": false,
                "isCurrentUserOwner": true,
                "isNowTimeValue": false,
                "timeFormat": "HH:mm",
                "isMultiple": false,
                "isAjax": false,
                "dataOptions": [],
                "ajaxDataUrl": "",
                "isChecked": false,
                "vif": "",
                "customCode": "",
                "invisible": true,
                "invisibleCondition": "",
                "invisibleInDataGrid": false,
                "invisibleLabel": false,
                "enableCustomValidation": false,
                "customValidationRule": "",
                "customValidationErrorMessage": "",
                "mask": "",
                "lookupOpenInModalDisabled": false,
                "editorMode": "javascript",
                "dataGridAvailableViews": [],
                "dataGridView": null,
                "dataGridAddRecordsText": "",
                "dataGridAddRecordText": "",
                "skipCrop": false,
                "disableRoundedStyle": false,
                "propName": "state"
              },
              {
                "type": "text",
                "name": "control_8347b160-5227-11ee-8eb0-6b93d594e479",
                "fieldName": "control_8347b160-5227-11ee-8eb0-6b93d594e479",
                "label": "Next Events",
                "order": 0,
                "defaultValue": "",
                "value": "",
                "className": "col-md-6",
                "readonly": false,
                "readonlyCondition": "",
                "placeholder": "",
                "required": false,
                "requiredCondition": "",
                "isMultiLine": false,
                "isInteger": false,
                "decimalPlace": 0,
                "isTodayValue": false,
                "isTodayValueCreated": true,
                "dateFormat": "mm/dd/yy hh:mm p",
                "timezone": null,
                "selectedDataGrid": null,
                "printedFileName": null,
                "buttonLabel": "",
                "dataForTemplate": null,
                "selectedOutputDataGrid": null,
                "templateRowKey": null,
                "isForDownload": false,
                "attachRecord": false,
                "isCurrentUser": false,
                "isCurrentUserOwner": true,
                "isNowTimeValue": false,
                "timeFormat": "HH:mm",
                "isMultiple": false,
                "isAjax": false,
                "dataOptions": [],
                "ajaxDataUrl": "",
                "isChecked": false,
                "vif": "",
                "customCode": "",
                "invisible": true,
                "invisibleCondition": "",
                "invisibleInDataGrid": false,
                "invisibleLabel": false,
                "enableCustomValidation": false,
                "customValidationRule": "",
                "customValidationErrorMessage": "",
                "mask": "",
                "lookupOpenInModalDisabled": false,
                "editorMode": "javascript",
                "dataGridAvailableViews": [],
                "dataGridView": null,
                "dataGridAddRecordsText": "",
                "dataGridAddRecordText": "",
                "skipCrop": false,
                "disableRoundedStyle": false,
                "propName": "nextEvents"
              },
              {
                "type": "user",
                "name": "control_83648830-5227-11ee-8eb0-6b93d594e479",
                "fieldName": "control_83648830-5227-11ee-8eb0-6b93d594e479",
                "label": "Last edited by",
                "order": 0,
                "defaultValue": "",
                "value": "",
                "className": "col-md-6",
                "readonly": true,
                "readonlyCondition": "",
                "placeholder": "",
                "required": false,
                "requiredCondition": "",
                "isMultiLine": false,
                "isInteger": false,
                "decimalPlace": 0,
                "isTodayValue": false,
                "isTodayValueCreated": true,
                "dateFormat": "mm/dd/yy hh:mm p",
                "timezone": null,
                "selectedDataGrid": null,
                "printedFileName": null,
                "buttonLabel": "",
                "dataForTemplate": null,
                "selectedOutputDataGrid": null,
                "templateRowKey": null,
                "isForDownload": false,
                "attachRecord": false,
                "isCurrentUser": false,
                "isCurrentUserOwner": true,
                "isNowTimeValue": false,
                "timeFormat": "HH:mm",
                "isMultiple": false,
                "isAjax": false,
                "dataOptions": [],
                "ajaxDataUrl": "",
                "isChecked": false,
                "vif": "",
                "customCode": "",
                "invisible": true,
                "invisibleCondition": "",
                "invisibleInDataGrid": false,
                "invisibleLabel": false,
                "enableCustomValidation": false,
                "customValidationRule": "",
                "customValidationErrorMessage": "",
                "mask": "",
                "lookupOpenInModalDisabled": false,
                "editorMode": "javascript",
                "dataGridAvailableViews": [],
                "dataGridView": null,
                "dataGridAddRecordsText": "",
                "dataGridAddRecordText": "",
                "skipCrop": false,
                "disableRoundedStyle": false,
                "propName": "lastEditedBy"
              },
              {
                "type": "datepicker",
                "name": "control_838556a0-5227-11ee-8eb0-6b93d594e479",
                "fieldName": "control_838556a0-5227-11ee-8eb0-6b93d594e479",
                "label": "Last edit date",
                "order": 0,
                "defaultValue": "",
                "value": "",
                "className": "col-md-6",
                "readonly": true,
                "readonlyCondition": "",
                "placeholder": "",
                "required": false,
                "requiredCondition": "",
                "isMultiLine": false,
                "isInteger": false,
                "decimalPlace": 0,
                "isTodayValue": false,
                "isTodayValueCreated": true,
                "dateFormat": "mm/dd/yy hh:mm p",
                "timezone": null,
                "selectedDataGrid": null,
                "printedFileName": null,
                "buttonLabel": "",
                "dataForTemplate": null,
                "selectedOutputDataGrid": null,
                "templateRowKey": null,
                "isForDownload": false,
                "attachRecord": false,
                "isCurrentUser": false,
                "isCurrentUserOwner": true,
                "isNowTimeValue": false,
                "timeFormat": "HH:mm",
                "isMultiple": false,
                "isAjax": false,
                "dataOptions": [],
                "ajaxDataUrl": "",
                "isChecked": false,
                "vif": "",
                "customCode": "",
                "invisible": true,
                "invisibleCondition": "",
                "invisibleInDataGrid": false,
                "invisibleLabel": false,
                "enableCustomValidation": false,
                "customValidationRule": "",
                "customValidationErrorMessage": "",
                "mask": "",
                "lookupOpenInModalDisabled": false,
                "editorMode": "javascript",
                "dataGridAvailableViews": [],
                "dataGridView": null,
                "dataGridAddRecordsText": "",
                "dataGridAddRecordText": "",
                "skipCrop": false,
                "disableRoundedStyle": false,
                "propName": "lastEditDate"
              }
            ]
          }
        ]
      },
      {
        "name": "section_275354",
        "label": "Time Entries",
        "clientKey": "section_275354",
        "order": 0,
        "rows": [
          {
            "name": "section_275354_row_433241",
            "label": "",
            "order": 0,
            "controls": [
              {
                "type": "datagrid",
                "name": "control_87083e10-53e3-11ee-8b82-09e16f6c6dd5",
                "fieldName": "control_87083e10-53e3-11ee-8b82-09e16f6c6dd5",
                "label": "Time Entries",
                "order": 0,
                "defaultValue": "",
                "value": "",
                "className": "col-md-12",
                "readonly": false,
                "readonlyCondition": "",
                "placeholder": "",
                "required": false,
                "requiredCondition": "",
                "isMultiLine": false,
                "isInteger": false,
                "decimalPlace": 0,
                "isTodayValue": false,
                "isTodayValueCreated": true,
                "dateFormat": "mm/dd/yy hh:mm p",
                "timezone": null,
                "selectedDataGrid": null,
                "printedFileName": null,
                "buttonLabel": "",
                "dataForTemplate": null,
                "selectedOutputDataGrid": null,
                "templateRowKey": null,
                "isForDownload": false,
                "attachRecord": false,
                "isCurrentUser": false,
                "isCurrentUserOwner": true,
                "isNowTimeValue": false,
                "timeFormat": "HH:mm",
                "isMultiple": false,
                "isAjax": false,
                "dataOptions": [],
                "ajaxDataUrl": "",
                "isChecked": false,
                "vif": "",
                "customCode": "",
                "invisible": false,
                "invisibleCondition": "",
                "invisibleInDataGrid": false,
                "invisibleLabel": true,
                "enableCustomValidation": false,
                "customValidationRule": "",
                "customValidationErrorMessage": "",
                "mask": "",
                "lookupOpenInModalDisabled": false,
                "editorMode": "javascript",
                "dataGridAvailableViews": [],
                "dataGridView": null,
                "dataGridAddRecordsText": "",
                "dataGridAddRecordText": "",
                "skipCrop": false,
                "disableRoundedStyle": false,
                "propName": "timeEntries_instance",
                "gridId": "resources"
              }
            ]
          }
        ],
        "labelPosition": "top",
        "isDynamic": false,
        "minInstance": 1,
        "maxInstance": 0,
        "instances": [],
        "vif": "",
        "collapsedByDefault": false
      },
      {
        "name": "section_958814",
        "label": "Method Operations",
        "clientKey": "section_958814",
        "order": 0,
        "rows": [
          {
            "name": "section_958814_row_65988",
            "label": "",
            "order": 0,
            "controls": [
              {
                "type": "datagrid",
                "name": "control_c9a79120-7428-11ee-bcbe-49a0cef063f3",
                "fieldName": "control_c9a79120-7428-11ee-bcbe-49a0cef063f3",
                "label": "Method Operation",
                "order": 0,
                "defaultValue": "",
                "value": "",
                "className": "col-md-12",
                "readonly": false,
                "readonlyCondition": "",
                "placeholder": "",
                "required": false,
                "requiredCondition": "",
                "isMultiLine": false,
                "isInteger": false,
                "decimalPlace": 0,
                "isTodayValue": false,
                "isTodayValueCreated": true,
                "dateFormat": "mm/dd/yy hh:mm p",
                "timezone": null,
                "selectedDataGrid": null,
                "printedFileName": null,
                "buttonLabel": "",
                "dataForTemplate": null,
                "selectedOutputDataGrid": null,
                "templateRowKey": null,
                "isForDownload": false,
                "attachRecord": false,
                "isCurrentUser": false,
                "isCurrentUserOwner": true,
                "isNowTimeValue": false,
                "timeFormat": "HH:mm",
                "isMultiple": false,
                "isAjax": false,
                "dataOptions": [],
                "ajaxDataUrl": "",
                "isChecked": false,
                "vif": "",
                "customCode": "",
                "invisible": false,
                "invisibleCondition": "",
                "invisibleLabel": true,
                "enableCustomValidation": false,
                "customValidationRule": "",
                "customValidationErrorMessage": "",
                "mask": "",
                "lookupOpenInModalDisabled": false,
                "editorMode": "javascript",
                "dataGridAvailableViews": [],
                "dataGridView": null,
                "dataGridAddRecordsText": "",
                "dataGridAddRecordText": "",
                "skipCrop": false,
                "disableRoundedStyle": false,
                "propName": "methodOperation",
                "gridId": "resources"
              }
            ]
          }
        ],
        "labelPosition": "top",
        "isDynamic": false,
        "minInstance": 1,
        "maxInstance": 0,
        "instances": [],
        "vif": "",
        "collapsedByDefault": false
      },
      {
        "name": "section_249318",
        "label": "Machine Run Time",
        "tooltip": "",
        "clientKey": "section_249318",
        "order": 0,
        "rows": [
          {
            "name": "section_249318_row_770391",
            "label": "",
            "order": 0,
            "controls": [
              {
                "type": "datagrid",
                "name": "control_015a4490-f2a6-11ee-a455-adeec78f747c",
                "fieldName": "control_015a4490-f2a6-11ee-a455-adeec78f747c",
                "label": "Machine Run Time",
                "order": 0,
                "defaultValue": "",
                "value": "",
                "className": "col-md-12",
                "readonly": false,
                "readonlyCondition": "",
                "placeholder": "",
                "required": false,
                "requiredCondition": "",
                "isMultiLine": false,
                "isInteger": false,
                "decimalPlace": 2,
                "expression": "",
                "isTodayValue": false,
                "isTodayValueCreated": true,
                "dateFormat": "mm/dd/yy hh:mm p",
                "timezone": null,
                "selectedDataGrid": null,
                "printedFileName": null,
                "buttonLabel": "",
                "dataForTemplate": null,
                "selectedOutputDataGrid": null,
                "templateRowKey": null,
                "isForDownload": false,
                "openInNewTab": false,
                "attachRecord": false,
                "isCurrentUser": false,
                "isCurrentUserOwner": true,
                "isNowTimeValue": false,
                "timeFormat": "HH:mm",
                "isMultiple": false,
                "isAjax": false,
                "dataOptions": [],
                "ajaxDataUrl": "",
                "isChecked": false,
                "vif": "",
                "customCode": "",
                "invisible": false,
                "invisibleCondition": "",
                "invisibleLabel": true,
                "enableCustomValidation": false,
                "customValidationRule": "",
                "customValidationErrorMessage": "",
                "mask": "",
                "lookupOpenInModalDisabled": false,
                "editorMode": "javascript",
                "dataGridAvailableViews": [],
                "dataGridView": null,
                "dataGridAddRecordsText": "",
                "dataGridAddRecordText": "",
                "skipCrop": false,
                "disableRoundedStyle": false,
                "propName": "machineRunTime_instance",
                "gridId": "resources"
              }
            ]
          }
        ],
        "labelPosition": "top",
        "isDynamic": false,
        "minInstance": 1,
        "maxInstance": 0,
        "instances": [],
        "vif": "",
        "collapsedByDefault": false,
        "tab": "default"
      }
    ],
    "layout": "collapse"
  },
  "source": "resources",
  "storageType": "dashboard",
  "title": "Resources"
}